{"name":"surf_intense","lightmapUrl":"https://raw.githubusercontent.com/RSCSurf/SurfMaps4/main/maps/surf_intense/lightmap.json?v=2048-11e83","leafPages":[{"first":0,"count":8192,"url":"https://raw.githubusercontent.com/RSCSurf/SurfMaps4/main/maps/surf_intense/geom/leafpage0.json?v=2048-11e83"},{"first":8192,"count":4178,"url":"https://raw.githubusercontent.com/RSCSurf/SurfMaps4/main/maps/surf_intense/geom/leafpage1.json?v=2048-11e83"}],"dispPages":[{"first":0,"count":0,"url":"https://raw.githubusercontent.com/RSCSurf/SurfMaps4/main/maps/surf_intense/geom/disppage0.json?v=2048-11e83"}],"materialPages":[{"first":0,"count":51,"url":"https://raw.githubusercontent.com/RSCSurf/SurfMaps4/main/maps/surf_intense/materials/matpage0.json?v=2048-11e83"}],"brushModelPages":[{"first":0,"count":1,"url":"https://raw.githubusercontent.com/RSCSurf/SurfMaps4/main/maps/surf_intense/geom/bsppage0.json?v=2048-11e83"},{"first":1,"count":135,"url":"https://raw.githubusercontent.com/RSCSurf/SurfMaps4/main/maps/surf_intense/geom/bsppage1.json?v=2048-11e83"}],"studioModelPages":[{"first":0,"count":3,"url":"https://raw.githubusercontent.com/RSCSurf/SurfMaps4/main/maps/surf_intense/geom/mdlpage0.json?v=2048-11e83"}],"vertLightingPages":[{"first":0,"count":9,"url":"https://raw.githubusercontent.com/RSCSurf/SurfMaps4/main/maps/surf_intense/geom/vhvpage0.json?v=2048-11e83"}],"visPages":[{"first":0,"count":4998,"url":"https://raw.githubusercontent.com/RSCSurf/SurfMaps4/main/maps/surf_intense/geom/vispage0.json?v=2048-11e83"}],"ambientPages":[{"first":0,"count":4096,"url":"https://raw.githubusercontent.com/RSCSurf/SurfMaps4/main/maps/surf_intense/geom/ambientpage0.json?v=2048-11e83"},{"first":4096,"count":4096,"url":"https://raw.githubusercontent.com/RSCSurf/SurfMaps4/main/maps/surf_intense/geom/ambientpage1.json?v=2048-11e83"},{"first":8192,"count":4096,"url":"https://raw.githubusercontent.com/RSCSurf/SurfMaps4/main/maps/surf_intense/geom/ambientpage2.json?v=2048-11e83"},{"first":12288,"count":82,"url":"https://raw.githubusercontent.com/RSCSurf/SurfMaps4/main/maps/surf_intense/geom/ambientpage3.json?v=2048-11e83"}],"entities":[{"skyMaterial":{"shader":"SourceUtils.Shaders.Sky","properties":[{"name":"cullFace","type":1,"value":false},{"name":"facePosX","type":4,"value":"https://raw.githubusercontent.com/RSCSurf/SurfMaps4/main/maps/surf_intense/materials/skybox/lost_at_seart.vtf.json?v=2048-11e83"},{"name":"faceNegX","type":4,"value":"https://raw.githubusercontent.com/RSCSurf/SurfMaps4/main/maps/surf_intense/materials/skybox/lost_at_sealf.vtf.json?v=2048-11e83"},{"name":"facePosY","type":4,"value":"https://raw.githubusercontent.com/RSCSurf/SurfMaps4/main/maps/surf_intense/materials/skybox/lost_at_seabk.vtf.json?v=2048-11e83"},{"name":"faceNegY","type":4,"value":"https://raw.githubusercontent.com/RSCSurf/SurfMaps4/main/maps/surf_intense/materials/skybox/lost_at_seaft.vtf.json?v=2048-11e83"},{"name":"facePosZ","type":4,"value":"https://raw.githubusercontent.com/RSCSurf/SurfMaps4/main/maps/surf_intense/materials/skybox/lost_at_seaup.vtf.json?v=2048-11e83"},{"name":"faceNegZ","type":4,"value":"https://raw.githubusercontent.com/RSCSurf/SurfMaps4/main/maps/surf_intense/materials/skybox/lost_at_seadn.vtf.json?v=2048-11e83"}]},"model":0,"classname":"worldspawn"},{"targetname":"stage1","classname":"trigger_multiple","origin":{"x":10578.6,"y":-7680.0,"z":4384.0}},{"targetname":"stage1","classname":"trigger_multiple","origin":{"x":10976.0,"y":-7680.0,"z":4384.0}},{"classname":"trigger_push","origin":{"x":14336.0,"y":-14336.0,"z":-1184.0}},{"classname":"func_dustmotes"},{"targetname":"dmg","classname":"filter_damage_type","origin":{"x":576.0,"y":-14336.0,"z":1504.0}},{"classname":"trigger_teleport","origin":{"x":3136.0,"y":-14336.0,"z":-254.0}},{"classname":"trigger_teleport","origin":{"x":6720.0,"y":-14336.0,"z":-254.0}},{"classname":"trigger_teleport","origin":{"x":6400.0,"y":-13632.0,"z":-254.0}},{"classname":"trigger_teleport","origin":{"x":6400.0,"y":-15040.0,"z":-254.0}},{"classname":"trigger_teleport","origin":{"x":7232.0,"y":-14336.0,"z":-1214.0}},{"classname":"trigger_teleport","origin":{"x":9280.0,"y":-14336.0,"z":-1214.0}},{"classname":"trigger_teleport","origin":{"x":8960.0,"y":-13632.0,"z":-1214.0}},{"classname":"trigger_teleport","origin":{"x":8960.0,"y":-15040.0,"z":-1214.0}},{"classname":"trigger_teleport","origin":{"x":8640.0,"y":-14336.0,"z":-1758.0}},{"classname":"trigger_teleport","origin":{"x":11264.0,"y":-14336.0,"z":-4222.0}},{"classname":"trigger_teleport","origin":{"x":10240.0,"y":-14336.0,"z":-3710.0}},{"classname":"trigger_teleport","origin":{"x":14336.0,"y":-14336.0,"z":-1184.0}},{"classname":"trigger_teleport","origin":{"x":15360.0,"y":-14336.0,"z":-254.0}},{"classname":"trigger_teleport","origin":{"x":13312.0,"y":-14336.0,"z":-254.0}},{"classname":"trigger_teleport","origin":{"x":14336.0,"y":-13312.0,"z":-254.0}},{"classname":"trigger_teleport","origin":{"x":14336.0,"y":-15360.0,"z":-254.0}},{"classname":"light","origin":{"x":1024.0,"y":-13952.0,"z":1152.0}},{"classname":"light","origin":{"x":1024.0,"y":-14720.0,"z":1152.0}},{"classname":"light","origin":{"x":1024.0,"y":-13952.0,"z":384.0}},{"classname":"light","origin":{"x":1024.0,"y":-14720.0,"z":384.0}},{"classname":"light","origin":{"x":2560.0,"y":-14720.0,"z":384.0}},{"classname":"light","origin":{"x":2560.0,"y":-13952.0,"z":384.0}},{"classname":"light","origin":{"x":2560.0,"y":-13952.0,"z":1152.0}},{"classname":"light","origin":{"x":2560.0,"y":-14720.0,"z":1152.0}},{"classname":"light","origin":{"x":4608.0,"y":-14720.0,"z":384.0}},{"classname":"light","origin":{"x":4608.0,"y":-13952.0,"z":384.0}},{"classname":"light","origin":{"x":4608.0,"y":-13952.0,"z":1152.0}},{"classname":"light","origin":{"x":4608.0,"y":-14720.0,"z":1152.0}},{"classname":"light","origin":{"x":6144.0,"y":-14720.0,"z":384.0}},{"classname":"light","origin":{"x":6144.0,"y":-13952.0,"z":384.0}},{"classname":"light","origin":{"x":6144.0,"y":-13952.0,"z":1152.0}},{"classname":"light","origin":{"x":6144.0,"y":-14720.0,"z":1152.0}},{"classname":"light","origin":{"x":6208.0,"y":-14336.0,"z":-768.0}},{"classname":"light","origin":{"x":8832.0,"y":-14336.0,"z":-768.0}},{"classname":"light","origin":{"x":7808.0,"y":-14720.0,"z":-2944.0}},{"classname":"light","origin":{"x":7808.0,"y":-14720.0,"z":-3392.0}},{"classname":"light","origin":{"x":7808.0,"y":-13952.0,"z":-3392.0}},{"classname":"light","origin":{"x":7808.0,"y":-13952.0,"z":-2944.0}},{"classname":"light","origin":{"x":8704.0,"y":-13952.0,"z":-3392.0}},{"classname":"light","origin":{"x":8704.0,"y":-13952.0,"z":-2944.0}},{"classname":"light","origin":{"x":8704.0,"y":-14720.0,"z":-3392.0}},{"classname":"light","origin":{"x":8704.0,"y":-14720.0,"z":-2944.0}},{"classname":"light","origin":{"x":11520.0,"y":-13952.0,"z":-3392.0}},{"classname":"light","origin":{"x":11520.0,"y":-13952.0,"z":-2944.0}},{"classname":"light","origin":{"x":11520.0,"y":-14720.0,"z":-3392.0}},{"classname":"light","origin":{"x":11520.0,"y":-14720.0,"z":-2944.0}},{"classname":"light","origin":{"x":14080.0,"y":-13952.0,"z":-3392.0}},{"classname":"light","origin":{"x":14080.0,"y":-13952.0,"z":-2944.0}},{"classname":"light","origin":{"x":14080.0,"y":-14720.0,"z":-3392.0}},{"classname":"light","origin":{"x":14080.0,"y":-14720.0,"z":-2944.0}},{"classname":"light","origin":{"x":14848.0,"y":-13952.0,"z":-3392.0}},{"classname":"light","origin":{"x":14848.0,"y":-13952.0,"z":-2944.0}},{"classname":"light","origin":{"x":14848.0,"y":-14720.0,"z":-3392.0}},{"classname":"light","origin":{"x":14848.0,"y":-14720.0,"z":-2944.0}},{"classname":"light","origin":{"x":14336.0,"y":-14336.0,"z":-1952.0}},{"classname":"light","origin":{"x":14336.0,"y":-14336.0,"z":-1568.0}},{"classname":"light","origin":{"x":14336.0,"y":-14336.0,"z":-1184.0}},{"classname":"light","origin":{"x":14336.0,"y":-14336.0,"z":-800.0}},{"classname":"light","origin":{"x":14336.0,"y":-14336.0,"z":-416.0}},{"classname":"light","origin":{"x":14336.0,"y":-14336.0,"z":0.0}},{"classname":"light","origin":{"x":14336.0,"y":-14336.0,"z":256.0}},{"classname":"light","origin":{"x":15360.0,"y":-15360.0,"z":256.0}},{"classname":"light","origin":{"x":14336.0,"y":-14336.0,"z":768.0}},{"classname":"light","origin":{"x":14336.0,"y":-14336.0,"z":1024.0}},{"classname":"light","origin":{"x":14336.0,"y":-14336.0,"z":1280.0}},{"classname":"light","origin":{"x":13312.0,"y":-15360.0,"z":256.0}},{"classname":"light","origin":{"x":13312.0,"y":-13312.0,"z":256.0}},{"classname":"light","origin":{"x":15360.0,"y":-13312.0,"z":256.0}},{"classname":"light","origin":{"x":13312.0,"y":-13312.0,"z":896.0}},{"classname":"light","origin":{"x":15360.0,"y":-13312.0,"z":896.0}},{"classname":"light","origin":{"x":15360.0,"y":-15360.0,"z":896.0}},{"classname":"light","origin":{"x":13312.0,"y":-15360.0,"z":896.0}},{"classname":"light","origin":{"x":8320.0,"y":-14656.0,"z":-768.0}},{"classname":"light","origin":{"x":8320.0,"y":-14016.0,"z":-768.0}},{"classname":"light","origin":{"x":400.0,"y":-14080.0,"z":1488.0}},{"classname":"light","origin":{"x":400.0,"y":-14592.0,"z":1488.0}},{"targetname":"essence_stage2","classname":"info_teleport_destination","origin":{"x":576.0,"y":-14336.0,"z":1448.0},"angles":{"x":0.0,"y":180.0,"z":0.0}},{"classname":"trigger_teleport","origin":{"x":10240.0,"y":-7680.0,"z":-2332.0}},{"classname":"trigger_push","origin":{"x":10240.0,"y":-7680.0,"z":-2336.0}},{"classname":"trigger_teleport","origin":{"x":10240.0,"y":-7680.0,"z":-446.0}},{"classname":"trigger_teleport","origin":{"x":10240.0,"y":-2560.0,"z":-6366.0}},{"classname":"trigger_teleport","origin":{"x":13280.0,"y":-7680.0,"z":1890.0}},{"classname":"trigger_teleport","origin":{"x":12800.0,"y":-7680.0,"z":2818.0}},{"targetname":"dmg","classname":"filter_damage_type","origin":{"x":10944.0,"y":-7680.0,"z":4352.0}},{"targetname":"essence_stage3","classname":"info_teleport_destination","origin":{"x":10944.0,"y":-7680.0,"z":4456.0},"angles":{"x":0.0,"y":180.0,"z":0.0}},{"classname":"light","origin":{"x":10240.0,"y":-8607.0,"z":3281.0}},{"classname":"env_fire","origin":{"x":10240.0,"y":-8608.0,"z":3208.0}},{"classname":"light","origin":{"x":10240.0,"y":-6753.0,"z":3281.0}},{"classname":"env_fire","origin":{"x":10240.0,"y":-6752.0,"z":3208.0}},{"classname":"light","origin":{"x":11264.0,"y":-6753.0,"z":3281.0}},{"classname":"env_fire","origin":{"x":11264.0,"y":-6752.0,"z":3208.0}},{"classname":"light","origin":{"x":11264.0,"y":-8607.0,"z":3281.0}},{"classname":"env_fire","origin":{"x":11264.0,"y":-8608.0,"z":3208.0}},{"classname":"light","origin":{"x":13280.0,"y":-6753.0,"z":3281.0}},{"classname":"env_fire","origin":{"x":13280.0,"y":-6752.0,"z":3208.0}},{"classname":"light","origin":{"x":13280.0,"y":-8607.0,"z":3281.0}},{"classname":"env_fire","origin":{"x":13280.0,"y":-8608.0,"z":3208.0}},{"classname":"light","origin":{"x":14336.0,"y":-6753.0,"z":3264.0}},{"classname":"env_fire","origin":{"x":14336.0,"y":-6752.0,"z":3191.0}},{"classname":"light","origin":{"x":14336.0,"y":-8607.0,"z":3264.0}},{"classname":"env_fire","origin":{"x":14336.0,"y":-8608.0,"z":3191.0}},{"classname":"light","origin":{"x":15360.0,"y":-6753.0,"z":3281.0}},{"classname":"env_fire","origin":{"x":15360.0,"y":-6752.0,"z":3208.0}},{"classname":"light","origin":{"x":15360.0,"y":-8607.0,"z":3281.0}},{"classname":"env_fire","origin":{"x":15360.0,"y":-8608.0,"z":3208.0}},{"classname":"light","origin":{"x":15360.0,"y":-6753.0,"z":2257.0}},{"classname":"env_fire","origin":{"x":15360.0,"y":-6752.0,"z":2184.0}},{"classname":"light","origin":{"x":15360.0,"y":-8607.0,"z":2257.0}},{"classname":"env_fire","origin":{"x":15360.0,"y":-8608.0,"z":2184.0}},{"classname":"light","origin":{"x":13280.0,"y":-6753.0,"z":2257.0}},{"classname":"env_fire","origin":{"x":13280.0,"y":-6752.0,"z":2184.0}},{"classname":"light","origin":{"x":13280.0,"y":-8607.0,"z":2257.0}},{"classname":"env_fire","origin":{"x":13280.0,"y":-8608.0,"z":2184.0}},{"classname":"light","origin":{"x":14304.0,"y":-6753.0,"z":2257.0}},{"classname":"env_fire","origin":{"x":14304.0,"y":-6752.0,"z":2184.0}},{"classname":"light","origin":{"x":14304.0,"y":-8607.0,"z":2257.0}},{"classname":"env_fire","origin":{"x":14304.0,"y":-8608.0,"z":2184.0}},{"classname":"light","origin":{"x":12288.0,"y":-6753.0,"z":2385.0}},{"classname":"env_fire","origin":{"x":12288.0,"y":-6752.0,"z":2312.0}},{"classname":"light","origin":{"x":12288.0,"y":-8607.0,"z":2385.0}},{"classname":"env_fire","origin":{"x":12288.0,"y":-8608.0,"z":2312.0}},{"classname":"light","origin":{"x":11264.0,"y":-6753.0,"z":2513.0}},{"classname":"env_fire","origin":{"x":11264.0,"y":-6752.0,"z":2440.0}},{"classname":"light","origin":{"x":11264.0,"y":-8607.0,"z":2513.0}},{"classname":"env_fire","origin":{"x":11264.0,"y":-8608.0,"z":2440.0}},{"classname":"light","origin":{"x":11008.0,"y":-5729.0,"z":593.0}},{"classname":"env_fire","origin":{"x":11008.0,"y":-5728.0,"z":520.0}},{"classname":"light","origin":{"x":10240.0,"y":-8607.0,"z":1745.0}},{"classname":"env_fire","origin":{"x":10240.0,"y":-8608.0,"z":1672.0}},{"classname":"env_fire","origin":{"x":9472.0,"y":-5728.0,"z":520.0}},{"classname":"light","origin":{"x":9472.0,"y":-5729.0,"z":593.0}},{"classname":"env_fire","origin":{"x":11008.0,"y":-9632.0,"z":520.0}},{"classname":"light","origin":{"x":11008.0,"y":-9631.0,"z":593.0}},{"classname":"light","origin":{"x":9472.0,"y":-9631.0,"z":593.0}},{"classname":"env_fire","origin":{"x":9472.0,"y":-9632.0,"z":520.0}},{"classname":"light","origin":{"x":10400.0,"y":-7840.0,"z":-1344.0}},{"classname":"light","origin":{"x":10400.0,"y":-7520.0,"z":-1792.0}},{"classname":"light","origin":{"x":10080.0,"y":-7520.0,"z":-2240.0}},{"classname":"light","origin":{"x":10080.0,"y":-7840.0,"z":-2688.0}},{"classname":"light","origin":{"x":10400.0,"y":-7840.0,"z":-3264.0}},{"classname":"light","origin":{"x":10400.0,"y":-7520.0,"z":-3840.0}},{"classname":"light","origin":{"x":11167.0,"y":-7680.0,"z":-4911.0}},{"classname":"env_fire","origin":{"x":11168.0,"y":-7680.0,"z":-4984.0}},{"classname":"light","origin":{"x":9313.0,"y":-7680.0,"z":-4911.0}},{"classname":"env_fire","origin":{"x":9312.0,"y":-7680.0,"z":-4984.0}},{"classname":"light","origin":{"x":9313.0,"y":-6656.0,"z":-5423.0}},{"classname":"env_fire","origin":{"x":9312.0,"y":-6656.0,"z":-5496.0}},{"classname":"light","origin":{"x":11167.0,"y":-6656.0,"z":-5423.0}},{"classname":"env_fire","origin":{"x":11168.0,"y":-6656.0,"z":-5496.0}},{"classname":"light","origin":{"x":9313.0,"y":-5632.0,"z":-5935.0}},{"classname":"env_fire","origin":{"x":9312.0,"y":-5632.0,"z":-6008.0}},{"classname":"light","origin":{"x":11167.0,"y":-5632.0,"z":-5935.0}},{"classname":"env_fire","origin":{"x":11168.0,"y":-5632.0,"z":-6008.0}},{"classname":"light","origin":{"x":9313.0,"y":-4608.0,"z":-5935.0}},{"classname":"env_fire","origin":{"x":9312.0,"y":-4608.0,"z":-6008.0}},{"classname":"light","origin":{"x":11167.0,"y":-4608.0,"z":-5935.0}},{"classname":"env_fire","origin":{"x":11168.0,"y":-4608.0,"z":-6008.0}},{"classname":"light","origin":{"x":9313.0,"y":-3584.0,"z":-6191.0}},{"classname":"env_fire","origin":{"x":9312.0,"y":-3584.0,"z":-6264.0}},{"classname":"light","origin":{"x":11167.0,"y":-3584.0,"z":-6191.0}},{"classname":"env_fire","origin":{"x":11168.0,"y":-3584.0,"z":-6264.0}},{"classname":"light","origin":{"x":9313.0,"y":-2560.0,"z":-6191.0}},{"classname":"env_fire","origin":{"x":9312.0,"y":-2560.0,"z":-6264.0}},{"classname":"light","origin":{"x":11167.0,"y":-2560.0,"z":-6191.0}},{"classname":"env_fire","origin":{"x":11168.0,"y":-2560.0,"z":-6264.0}},{"classname":"light","origin":{"x":9313.0,"y":-1568.0,"z":-6191.0}},{"classname":"env_fire","origin":{"x":9312.0,"y":-1568.0,"z":-6264.0}},{"classname":"light","origin":{"x":11167.0,"y":-1568.0,"z":-6191.0}},{"classname":"env_fire","origin":{"x":11168.0,"y":-1568.0,"z":-6264.0}},{"classname":"light","origin":{"x":9313.0,"y":-512.0,"z":-6191.0}},{"classname":"env_fire","origin":{"x":9312.0,"y":-512.0,"z":-6264.0}},{"classname":"light","origin":{"x":11167.0,"y":-512.0,"z":-6191.0}},{"classname":"env_fire","origin":{"x":11168.0,"y":-512.0,"z":-6264.0}},{"classname":"light","origin":{"x":9313.0,"y":512.0,"z":-6191.0}},{"classname":"env_fire","origin":{"x":9312.0,"y":512.0,"z":-6264.0}},{"classname":"light","origin":{"x":11167.0,"y":512.0,"z":-6191.0}},{"classname":"env_fire","origin":{"x":11168.0,"y":512.0,"z":-6264.0}},{"classname":"light","origin":{"x":9313.0,"y":2560.0,"z":-6191.0}},{"classname":"env_fire","origin":{"x":9312.0,"y":2560.0,"z":-6264.0}},{"classname":"light","origin":{"x":11167.0,"y":2560.0,"z":-6191.0}},{"classname":"env_fire","origin":{"x":11168.0,"y":2560.0,"z":-6264.0}},{"classname":"light","origin":{"x":10240.0,"y":3551.0,"z":-5871.0}},{"classname":"env_fire","origin":{"x":10240.0,"y":3552.0,"z":-5944.0}},{"model":27,"clusters":[303,304],"classname":"func_brush","origin":{"x":10240.0,"y":3552.0,"z":-6048.0}},{"classname":"light","origin":{"x":9824.0,"y":-7680.0,"z":4272.0}},{"classname":"env_fire","origin":{"x":9824.0,"y":-7680.0,"z":4224.0}},{"classname":"env_fire","origin":{"x":9312.0,"y":1536.0,"z":-6264.0}},{"classname":"light","origin":{"x":9313.0,"y":1536.0,"z":-6191.0}},{"classname":"env_fire","origin":{"x":11168.0,"y":1536.0,"z":-6264.0}},{"classname":"light","origin":{"x":11167.0,"y":1536.0,"z":-6191.0}},{"classname":"light","origin":{"x":10240.0,"y":2048.0,"z":-6080.0}},{"classname":"light","origin":{"x":10080.0,"y":-7840.0,"z":-640.0}},{"classname":"light","origin":{"x":10240.0,"y":-7680.0,"z":-192.0}},{"classname":"env_fire","origin":{"x":10240.0,"y":-6752.0,"z":1672.0}},{"classname":"light","origin":{"x":10240.0,"y":-6753.0,"z":1745.0}},{"classname":"light","origin":{"x":11072.0,"y":-6912.0,"z":1504.0}},{"classname":"light","origin":{"x":11072.0,"y":-7168.0,"z":1504.0}},{"classname":"light","origin":{"x":11072.0,"y":-7424.0,"z":1504.0}},{"classname":"light","origin":{"x":11072.0,"y":-8192.0,"z":1504.0}},{"classname":"light","origin":{"x":11072.0,"y":-7936.0,"z":1504.0}},{"classname":"light","origin":{"x":11072.0,"y":-7680.0,"z":1504.0}},{"classname":"light","origin":{"x":11072.0,"y":-8448.0,"z":1504.0}},{"classname":"trigger_teleport","origin":{"x":10496.0,"y":-7680.0,"z":1090.0}},{"classname":"trigger_teleport","origin":{"x":10240.0,"y":-1024.0,"z":-6336.0}},{"classname":"trigger_teleport","origin":{"x":9328.0,"y":-1024.0,"z":-6336.0}},{"classname":"trigger_teleport","origin":{"x":11152.0,"y":-1024.0,"z":-6336.0}},{"classname":"trigger_teleport","origin":{"x":9296.0,"y":-1024.0,"z":-6336.0}},{"classname":"trigger_teleport","origin":{"x":11184.0,"y":-1024.0,"z":-6336.0}},{"classname":"trigger_teleport","origin":{"x":9296.0,"y":1024.0,"z":-5824.0}},{"classname":"trigger_teleport","origin":{"x":9328.0,"y":1024.0,"z":-5824.0}},{"classname":"trigger_teleport","origin":{"x":10240.0,"y":1024.0,"z":-5824.0}},{"classname":"trigger_teleport","origin":{"x":11184.0,"y":1024.0,"z":-5824.0}},{"classname":"trigger_teleport","origin":{"x":11152.0,"y":1024.0,"z":-5824.0}},{"classname":"trigger_teleport","origin":{"x":9296.0,"y":1024.0,"z":-6848.0}},{"classname":"trigger_teleport","origin":{"x":9328.0,"y":1024.0,"z":-6848.0}},{"classname":"trigger_teleport","origin":{"x":10240.0,"y":1024.0,"z":-6848.0}},{"classname":"trigger_teleport","origin":{"x":11184.0,"y":1024.0,"z":-6848.0}},{"classname":"trigger_teleport","origin":{"x":11152.0,"y":1024.0,"z":-6848.0}},{"classname":"trigger_push","origin":{"x":-10256.0,"y":4352.0,"z":1184.0}},{"classname":"light","origin":{"x":-10608.0,"y":4160.0,"z":1328.0}},{"classname":"light","origin":{"x":-9728.0,"y":3904.0,"z":1536.0}},{"classname":"light","origin":{"x":-9728.0,"y":4800.0,"z":1536.0}},{"classname":"light","origin":{"x":-9216.0,"y":4800.0,"z":1536.0}},{"classname":"light","origin":{"x":-9216.0,"y":3904.0,"z":1536.0}},{"classname":"light","origin":{"x":-8704.0,"y":4800.0,"z":1536.0}},{"classname":"light","origin":{"x":-8704.0,"y":3904.0,"z":1536.0}},{"classname":"light","origin":{"x":-8192.0,"y":4800.0,"z":1536.0}},{"classname":"light","origin":{"x":-8192.0,"y":3904.0,"z":1536.0}},{"classname":"light","origin":{"x":-7680.0,"y":4800.0,"z":1536.0}},{"classname":"light","origin":{"x":-7680.0,"y":3904.0,"z":1536.0}},{"classname":"light","origin":{"x":-7168.0,"y":4800.0,"z":1536.0}},{"classname":"light","origin":{"x":-7168.0,"y":3904.0,"z":1536.0}},{"classname":"light","origin":{"x":-6656.0,"y":4800.0,"z":1536.0}},{"classname":"light","origin":{"x":-6656.0,"y":3904.0,"z":1536.0}},{"classname":"light","origin":{"x":-6144.0,"y":4800.0,"z":1536.0}},{"classname":"light","origin":{"x":-6144.0,"y":3904.0,"z":1536.0}},{"classname":"light","origin":{"x":-9216.0,"y":4800.0,"z":512.0}},{"classname":"light","origin":{"x":-9216.0,"y":3904.0,"z":512.0}},{"classname":"light","origin":{"x":-8704.0,"y":4800.0,"z":512.0}},{"classname":"light","origin":{"x":-8704.0,"y":3904.0,"z":512.0}},{"classname":"light","origin":{"x":-8192.0,"y":4800.0,"z":512.0}},{"classname":"light","origin":{"x":-8192.0,"y":3904.0,"z":512.0}},{"classname":"light","origin":{"x":-7680.0,"y":4800.0,"z":512.0}},{"classname":"light","origin":{"x":-7680.0,"y":3904.0,"z":512.0}},{"classname":"light","origin":{"x":-7168.0,"y":4800.0,"z":512.0}},{"classname":"light","origin":{"x":-7168.0,"y":3904.0,"z":512.0}},{"classname":"light","origin":{"x":-6656.0,"y":4800.0,"z":512.0}},{"classname":"light","origin":{"x":-6656.0,"y":3904.0,"z":512.0}},{"classname":"light","origin":{"x":-6144.0,"y":4800.0,"z":512.0}},{"classname":"light","origin":{"x":-6144.0,"y":3904.0,"z":512.0}},{"classname":"light","origin":{"x":-8960.0,"y":5760.0,"z":512.0}},{"classname":"light","origin":{"x":-9344.0,"y":5760.0,"z":-128.0}},{"classname":"light","origin":{"x":-9760.0,"y":5760.0,"z":-512.0}},{"classname":"light","origin":{"x":-8864.0,"y":2944.0,"z":-544.0}},{"classname":"light","origin":{"x":-8960.0,"y":2944.0,"z":512.0}},{"classname":"light","origin":{"x":-9344.0,"y":2944.0,"z":-128.0}},{"classname":"light","origin":{"x":-9760.0,"y":3296.0,"z":-512.0}},{"classname":"light","origin":{"x":-9760.0,"y":5408.0,"z":-512.0}},{"classname":"light","origin":{"x":-9824.0,"y":4352.0,"z":-256.0}},{"classname":"light","origin":{"x":-8864.0,"y":3328.0,"z":-544.0}},{"classname":"light","origin":{"x":-8864.0,"y":4352.0,"z":-544.0}},{"classname":"light","origin":{"x":-8864.0,"y":3840.0,"z":-544.0}},{"classname":"light","origin":{"x":-8864.0,"y":4864.0,"z":-544.0}},{"classname":"light","origin":{"x":-8864.0,"y":5376.0,"z":-544.0}},{"classname":"light","origin":{"x":-8960.0,"y":5760.0,"z":-512.0}},{"classname":"light","origin":{"x":-9440.0,"y":4864.0,"z":-896.0}},{"classname":"light","origin":{"x":-9440.0,"y":4352.0,"z":-896.0}},{"classname":"light","origin":{"x":-9440.0,"y":3840.0,"z":-896.0}},{"classname":"light","origin":{"x":-8960.0,"y":4864.0,"z":-896.0}},{"classname":"light","origin":{"x":-8960.0,"y":4352.0,"z":-896.0}},{"classname":"light","origin":{"x":-8960.0,"y":3840.0,"z":-896.0}},{"classname":"light","origin":{"x":-9952.0,"y":4864.0,"z":-896.0}},{"classname":"light","origin":{"x":-9952.0,"y":4352.0,"z":-896.0}},{"classname":"light","origin":{"x":-9952.0,"y":3840.0,"z":-896.0}},{"classname":"light","origin":{"x":-9920.0,"y":4864.0,"z":-1152.0}},{"classname":"light","origin":{"x":-9920.0,"y":4352.0,"z":-1152.0}},{"classname":"light","origin":{"x":-9920.0,"y":3840.0,"z":-1152.0}},{"classname":"light","origin":{"x":-9440.0,"y":4864.0,"z":-1152.0}},{"classname":"light","origin":{"x":-9440.0,"y":4352.0,"z":-1152.0}},{"classname":"light","origin":{"x":-9440.0,"y":3840.0,"z":-1152.0}},{"classname":"light","origin":{"x":-8960.0,"y":4864.0,"z":-1152.0}},{"classname":"light","origin":{"x":-8960.0,"y":4352.0,"z":-1152.0}},{"classname":"light","origin":{"x":-8960.0,"y":3840.0,"z":-1152.0}},{"classname":"light","origin":{"x":-8960.0,"y":4864.0,"z":-1408.0}},{"classname":"light","origin":{"x":-8960.0,"y":4352.0,"z":-1408.0}},{"classname":"light","origin":{"x":-8960.0,"y":3840.0,"z":-1408.0}},{"classname":"light","origin":{"x":-9440.0,"y":4864.0,"z":-1376.0}},{"classname":"light","origin":{"x":-9440.0,"y":4352.0,"z":-1376.0}},{"classname":"light","origin":{"x":-9440.0,"y":3840.0,"z":-1376.0}},{"classname":"light","origin":{"x":-9920.0,"y":4864.0,"z":-1376.0}},{"classname":"light","origin":{"x":-9920.0,"y":4352.0,"z":-1376.0}},{"classname":"light","origin":{"x":-9920.0,"y":3840.0,"z":-1376.0}},{"Brightness":{"R":255,"G":255,"B":255,"A":200},"Ambient":{"R":255,"G":255,"B":255,"A":20},"BrightnessHdr":{"R":255,"G":255,"B":255,"A":1},"AmbientHdr":{"R":255,"G":255,"B":255,"A":1},"BrightnessScaleHdr":1.0,"AmbientScaleHdr":1.0,"Pitch":-62.0,"classname":"light_environment","origin":{"x":-12672.0,"y":4352.0,"z":-1120.0},"angles":{"x":-62.0,"y":123.0,"z":0.0}},{"classname":"light","origin":{"x":-14080.0,"y":3904.0,"z":-4000.0}},{"classname":"light","origin":{"x":-14080.0,"y":4800.0,"z":-4000.0}},{"classname":"light","origin":{"x":-13312.0,"y":3904.0,"z":-4096.0}},{"classname":"light","origin":{"x":-13312.0,"y":4800.0,"z":-4096.0}},{"classname":"light","origin":{"x":-12800.0,"y":3904.0,"z":-4096.0}},{"classname":"light","origin":{"x":-12800.0,"y":4800.0,"z":-4096.0}},{"classname":"light","origin":{"x":-12288.0,"y":3904.0,"z":-4096.0}},{"classname":"light","origin":{"x":-12288.0,"y":4800.0,"z":-4096.0}},{"classname":"light","origin":{"x":-11776.0,"y":3904.0,"z":-4096.0}},{"classname":"light","origin":{"x":-11776.0,"y":4800.0,"z":-4096.0}},{"classname":"light","origin":{"x":-11264.0,"y":3904.0,"z":-4096.0}},{"classname":"light","origin":{"x":-11264.0,"y":4800.0,"z":-4096.0}},{"classname":"light","origin":{"x":-10752.0,"y":3904.0,"z":-4096.0}},{"classname":"light","origin":{"x":-10752.0,"y":4800.0,"z":-4096.0}},{"classname":"light","origin":{"x":-10240.0,"y":3904.0,"z":-4096.0}},{"classname":"light","origin":{"x":-10240.0,"y":4800.0,"z":-4096.0}},{"classname":"light","origin":{"x":-9760.0,"y":3904.0,"z":-4096.0}},{"classname":"light","origin":{"x":-9760.0,"y":4800.0,"z":-4096.0}},{"classname":"light","origin":{"x":-10608.0,"y":4544.0,"z":1328.0}},{"classname":"trigger_teleport","origin":{"x":-8448.0,"y":4352.0,"z":1058.0}},{"classname":"trigger_teleport","origin":{"x":-5408.0,"y":4352.0,"z":34.0}},{"classname":"trigger_teleport","origin":{"x":-7696.0,"y":4352.0,"z":34.0}},{"classname":"trigger_teleport","origin":{"x":-6416.0,"y":4352.0,"z":514.0}},{"classname":"trigger_teleport","origin":{"x":-8976.0,"y":5744.0,"z":-238.0}},{"classname":"trigger_teleport","origin":{"x":-8976.0,"y":2960.0,"z":-238.0}},{"classname":"trigger_teleport","origin":{"x":-9552.0,"y":4352.0,"z":-734.0}},{"classname":"trigger_teleport","origin":{"x":-8800.0,"y":3120.0,"z":-734.0}},{"classname":"trigger_teleport","origin":{"x":-8800.0,"y":5584.0,"z":-734.0}},{"classname":"trigger_teleport","origin":{"x":-8608.0,"y":4352.0,"z":-734.0}},{"classname":"trigger_teleport","origin":{"x":-10016.0,"y":4352.0,"z":-990.0}},{"classname":"trigger_teleport","origin":{"x":-9440.0,"y":5200.0,"z":-990.0}},{"classname":"trigger_teleport","origin":{"x":-9088.0,"y":4352.0,"z":-1246.0}},{"classname":"trigger_teleport","origin":{"x":-9440.0,"y":3504.0,"z":-990.0}},{"classname":"trigger_teleport","origin":{"x":-9920.0,"y":5200.0,"z":-1246.0}},{"classname":"trigger_teleport","origin":{"x":-9920.0,"y":3504.0,"z":-1246.0}},{"classname":"trigger_teleport","origin":{"x":-10256.0,"y":4352.0,"z":-1246.0}},{"classname":"trigger_teleport","origin":{"x":-8848.0,"y":4352.0,"z":-990.0}},{"classname":"trigger_teleport","origin":{"x":-11088.0,"y":4352.0,"z":-2798.0}},{"classname":"trigger_teleport","origin":{"x":-13408.0,"y":4352.0,"z":-3550.0}},{"classname":"trigger_teleport","origin":{"x":-15056.0,"y":4352.0,"z":-3550.0}},{"classname":"trigger_teleport","origin":{"x":-14592.0,"y":5200.0,"z":-3550.0}},{"classname":"trigger_teleport","origin":{"x":-14592.0,"y":3504.0,"z":-3550.0}},{"classname":"trigger_teleport","origin":{"x":-14272.0,"y":4352.0,"z":-4286.0}},{"classname":"trigger_teleport","origin":{"x":-12544.0,"y":4352.0,"z":-4574.0}},{"classname":"trigger_teleport","origin":{"x":-7824.0,"y":4352.0,"z":-4318.0}},{"targetname":"essence_stage4","classname":"info_teleport_destination","origin":{"x":-10624.0,"y":4352.0,"z":1752.0},"angles":{"x":0.0,"y":0.0,"z":0.0}},{"classname":"light","origin":{"x":-10624.0,"y":4800.0,"z":1792.0}},{"classname":"light","origin":{"x":-10624.0,"y":3904.0,"z":1792.0}},{"targetname":"dmg","classname":"filter_damage_type","origin":{"x":-10624.0,"y":4352.0,"z":1792.0}},{"classname":"info_ladder"},{"classname":"trigger_push","origin":{"x":15312.0,"y":12160.0,"z":-468.0}},{"classname":"trigger_push","origin":{"x":12288.0,"y":12528.0,"z":-1044.0}},{"classname":"info_ladder"},{"Brightness":{"R":255,"G":255,"B":255,"A":200},"Ambient":{"R":255,"G":255,"B":255,"A":20},"BrightnessHdr":{"R":255,"G":255,"B":255,"A":1},"AmbientHdr":{"R":255,"G":255,"B":255,"A":1},"BrightnessScaleHdr":1.0,"AmbientScaleHdr":1.0,"Pitch":-65.0,"classname":"light_environment","origin":{"x":13824.0,"y":13824.0,"z":-256.0},"angles":{"x":-65.0,"y":275.0,"z":0.0}},{"classname":"light","origin":{"x":15328.0,"y":13824.0,"z":-576.0}},{"classname":"light","origin":{"x":15360.0,"y":13792.0,"z":-832.0}},{"classname":"light","origin":{"x":15392.0,"y":13824.0,"z":-1088.0}},{"classname":"light","origin":{"x":15360.0,"y":13856.0,"z":-1344.0}},{"classname":"light","origin":{"x":15360.0,"y":13856.0,"z":-2368.0}},{"classname":"light","origin":{"x":15392.0,"y":13824.0,"z":-2112.0}},{"classname":"light","origin":{"x":15360.0,"y":13792.0,"z":-1856.0}},{"classname":"light","origin":{"x":15328.0,"y":13824.0,"z":-1600.0}},{"classname":"light","origin":{"x":15296.0,"y":15104.0,"z":-1376.0}},{"classname":"light","origin":{"x":13824.0,"y":15360.0,"z":-1824.0}},{"classname":"light","origin":{"x":12304.0,"y":15344.0,"z":-1824.0}},{"targetname":"ex0n2","classname":"info_teleport_destination","origin":{"x":12288.0,"y":15360.0,"z":-1152.0},"angles":{"x":0.0,"y":0.0,"z":0.0}},{"targetname":"dmg","classname":"filter_damage_type","origin":{"x":12288.0,"y":15360.0,"z":-1184.0}},{"classname":"trigger_teleport","origin":{"x":13824.0,"y":13824.0,"z":-2527.5}},{"classname":"trigger_teleport","origin":{"x":15248.0,"y":13824.0,"z":-511.5}},{"classname":"trigger_teleport","origin":{"x":15360.0,"y":13712.0,"z":-767.5}},{"classname":"trigger_teleport","origin":{"x":15472.0,"y":13824.0,"z":-1023.5}},{"classname":"trigger_teleport","origin":{"x":15360.0,"y":13936.0,"z":-1279.5}},{"classname":"trigger_teleport","origin":{"x":15360.0,"y":13936.0,"z":-2303.5}},{"classname":"trigger_teleport","origin":{"x":15360.0,"y":13712.0,"z":-1791.5}},{"classname":"trigger_teleport","origin":{"x":15248.0,"y":13824.0,"z":-1535.5}},{"classname":"trigger_teleport","origin":{"x":15472.0,"y":13824.0,"z":-2047.5}},{"classname":"trigger_teleport","origin":{"x":15360.0,"y":13824.0,"z":-2448.0}},{"model":83,"clusters":[63,84],"classname":"func_brush","origin":{"x":13925.2,"y":14601.5,"z":-2524.0}},{"targetname":"beam1","classname":"info_target","origin":{"x":-184.0,"y":-20.0,"z":-1552.0},"angles":{"x":0.0,"y":0.0,"z":0.0}},{"targetname":"beam2","classname":"info_target","origin":{"x":-184.0,"y":20.0,"z":-1552.0},"angles":{"x":0.0,"y":0.0,"z":0.0}},{"targetname":"beam7","classname":"info_target","origin":{"x":20.0,"y":-184.0,"z":-1552.0},"angles":{"x":0.0,"y":0.0,"z":0.0}},{"targetname":"beam8","classname":"info_target","origin":{"x":-20.0,"y":-184.0,"z":-1552.0},"angles":{"x":0.0,"y":0.0,"z":0.0}},{"targetname":"beam5","classname":"info_target","origin":{"x":184.0,"y":20.0,"z":-1552.0},"angles":{"x":0.0,"y":0.0,"z":0.0}},{"targetname":"beam6","classname":"info_target","origin":{"x":184.0,"y":-20.0,"z":-1552.0},"angles":{"x":0.0,"y":0.0,"z":0.0}},{"targetname":"beam3","classname":"info_target","origin":{"x":-20.0,"y":184.0,"z":-1552.0},"angles":{"x":0.0,"y":0.0,"z":0.0}},{"targetname":"beam4","classname":"info_target","origin":{"x":20.0,"y":184.0,"z":-1552.0},"angles":{"x":0.0,"y":0.0,"z":0.0}},{"targetname":"beam9","classname":"info_target","origin":{"x":-160.0,"y":-160.0,"z":-1648.0},"angles":{"x":0.0,"y":0.0,"z":0.0}},{"targetname":"beam10","classname":"info_target","origin":{"x":-160.0,"y":160.0,"z":-1648.0},"angles":{"x":0.0,"y":0.0,"z":0.0}},{"targetname":"beam11","classname":"info_target","origin":{"x":160.0,"y":160.0,"z":-1648.0},"angles":{"x":0.0,"y":0.0,"z":0.0}},{"targetname":"beam12","classname":"info_target","origin":{"x":160.0,"y":-160.0,"z":-1648.0},"angles":{"x":0.0,"y":0.0,"z":0.0}},{"targetname":"beam_target","classname":"info_target","origin":{"x":0.0,"y":0.0,"z":-1422.0},"angles":{"x":0.0,"y":0.0,"z":0.0}},{"classname":"env_beam","origin":{"x":-184.0,"y":-20.0,"z":-1540.0}},{"classname":"env_beam","origin":{"x":-184.0,"y":20.0,"z":-1540.0}},{"classname":"env_beam","origin":{"x":-20.0,"y":184.0,"z":-1540.0}},{"classname":"env_beam","origin":{"x":20.0,"y":184.0,"z":-1540.0}},{"classname":"env_beam","origin":{"x":184.0,"y":20.0,"z":-1540.0}},{"classname":"env_beam","origin":{"x":184.0,"y":-20.0,"z":-1540.0}},{"classname":"env_beam","origin":{"x":20.0,"y":-184.0,"z":-1540.0}},{"classname":"env_beam","origin":{"x":-20.0,"y":-184.0,"z":-1540.0}},{"classname":"env_beam","origin":{"x":-160.0,"y":-160.0,"z":-1636.0}},{"classname":"env_beam","origin":{"x":-160.0,"y":160.0,"z":-1636.0}},{"classname":"env_beam","origin":{"x":160.0,"y":160.0,"z":-1636.0}},{"classname":"env_beam","origin":{"x":160.0,"y":-160.0,"z":-1636.0}},{"targetname":"beam_target2","classname":"info_target","origin":{"x":0.0,"y":0.0,"z":-1192.0},"angles":{"x":0.0,"y":0.0,"z":0.0}},{"classname":"env_sprite","origin":{"x":0.0,"y":0.0,"z":-1192.0}},{"classname":"env_beam","origin":{"x":0.0,"y":0.0,"z":-1408.0}},{"classname":"trigger_teleport","origin":{"x":0.0,"y":0.0,"z":-1192.0}},{"classname":"trigger_teleport","origin":{"x":0.0,"y":0.0,"z":-1964.0}},{"model":86,"clusters":[1127,1138,1141,1145,1146,2260,2263,2264,2267,2279,3662,3665,3666,3669,3681,4405,4416,4419,4420,4421],"classname":"func_brush","origin":{"x":0.0,"y":0.0,"z":-1192.0}},{"classname":"info_ladder"},{"classname":"info_ladder"},{"classname":"info_ladder"},{"classname":"info_ladder"},{"classname":"info_ladder"},{"classname":"light","origin":{"x":448.0,"y":448.0,"z":-1520.0}},{"classname":"light","origin":{"x":-448.0,"y":448.0,"z":-1520.0}},{"classname":"light","origin":{"x":-448.0,"y":-448.0,"z":-1520.0}},{"classname":"light","origin":{"x":448.0,"y":-448.0,"z":-1520.0}},{"classname":"light","origin":{"x":-448.0,"y":-448.0,"z":-1072.0}},{"classname":"light","origin":{"x":448.0,"y":-448.0,"z":-1072.0}},{"classname":"light","origin":{"x":448.0,"y":448.0,"z":-1072.0}},{"classname":"light","origin":{"x":-448.0,"y":448.0,"z":-1072.0}},{"classname":"ambient_generic","origin":{"x":0.0,"y":0.0,"z":-1360.0}},{"classname":"func_dustmotes"},{"classname":"info_player_terrorist","origin":{"x":-448.0,"y":448.0,"z":-655.0},"angles":{"x":0.0,"y":0.0,"z":0.0}},{"classname":"info_player_terrorist","origin":{"x":-448.0,"y":384.0,"z":-655.0},"angles":{"x":0.0,"y":0.0,"z":0.0}},{"classname":"info_player_terrorist","origin":{"x":-448.0,"y":320.0,"z":-655.0},"angles":{"x":0.0,"y":0.0,"z":0.0}},{"classname":"info_player_terrorist","origin":{"x":-448.0,"y":256.0,"z":-655.0},"angles":{"x":0.0,"y":0.0,"z":0.0}},{"classname":"info_player_terrorist","origin":{"x":-448.0,"y":192.0,"z":-655.0},"angles":{"x":0.0,"y":0.0,"z":0.0}},{"classname":"info_player_terrorist","origin":{"x":-448.0,"y":128.0,"z":-655.0},"angles":{"x":0.0,"y":0.0,"z":0.0}},{"classname":"info_player_terrorist","origin":{"x":-448.0,"y":64.0,"z":-655.0},"angles":{"x":0.0,"y":0.0,"z":0.0}},{"classname":"info_player_terrorist","origin":{"x":-448.0,"y":0.0,"z":-655.0},"angles":{"x":0.0,"y":0.0,"z":0.0}},{"classname":"info_player_terrorist","origin":{"x":-448.0,"y":-64.0,"z":-655.0},"angles":{"x":0.0,"y":0.0,"z":0.0}},{"classname":"info_player_terrorist","origin":{"x":-448.0,"y":-128.0,"z":-655.0},"angles":{"x":0.0,"y":0.0,"z":0.0}},{"classname":"info_player_terrorist","origin":{"x":-448.0,"y":-192.0,"z":-655.0},"angles":{"x":0.0,"y":0.0,"z":0.0}},{"classname":"info_player_terrorist","origin":{"x":-448.0,"y":-256.0,"z":-655.0},"angles":{"x":0.0,"y":0.0,"z":0.0}},{"classname":"info_player_terrorist","origin":{"x":-448.0,"y":-320.0,"z":-655.0},"angles":{"x":0.0,"y":0.0,"z":0.0}},{"classname":"info_player_terrorist","origin":{"x":-448.0,"y":-384.0,"z":-655.0},"angles":{"x":0.0,"y":0.0,"z":0.0}},{"classname":"info_player_terrorist","origin":{"x":-448.0,"y":-448.0,"z":-655.0},"angles":{"x":0.0,"y":0.0,"z":0.0}},{"classname":"info_player_terrorist","origin":{"x":-384.0,"y":-448.0,"z":-655.0},"angles":{"x":0.0,"y":0.0,"z":0.0}},{"classname":"info_player_terrorist","origin":{"x":-384.0,"y":-384.0,"z":-655.0},"angles":{"x":0.0,"y":0.0,"z":0.0}},{"classname":"info_player_terrorist","origin":{"x":-384.0,"y":-320.0,"z":-655.0},"angles":{"x":0.0,"y":0.0,"z":0.0}},{"classname":"info_player_terrorist","origin":{"x":-384.0,"y":-256.0,"z":-655.0},"angles":{"x":0.0,"y":0.0,"z":0.0}},{"classname":"info_player_terrorist","origin":{"x":-384.0,"y":-192.0,"z":-655.0},"angles":{"x":0.0,"y":0.0,"z":0.0}},{"classname":"info_player_terrorist","origin":{"x":-384.0,"y":-128.0,"z":-655.0},"angles":{"x":0.0,"y":0.0,"z":0.0}},{"classname":"info_player_terrorist","origin":{"x":-384.0,"y":-64.0,"z":-655.0},"angles":{"x":0.0,"y":0.0,"z":0.0}},{"classname":"info_player_terrorist","origin":{"x":-384.0,"y":0.0,"z":-655.0},"angles":{"x":0.0,"y":0.0,"z":0.0}},{"classname":"info_player_terrorist","origin":{"x":-384.0,"y":64.0,"z":-655.0},"angles":{"x":0.0,"y":0.0,"z":0.0}},{"classname":"info_player_terrorist","origin":{"x":-384.0,"y":128.0,"z":-655.0},"angles":{"x":0.0,"y":0.0,"z":0.0}},{"classname":"info_player_terrorist","origin":{"x":-384.0,"y":192.0,"z":-655.0},"angles":{"x":0.0,"y":0.0,"z":0.0}},{"classname":"info_player_terrorist","origin":{"x":-384.0,"y":256.0,"z":-655.0},"angles":{"x":0.0,"y":0.0,"z":0.0}},{"classname":"info_player_terrorist","origin":{"x":-384.0,"y":320.0,"z":-655.0},"angles":{"x":0.0,"y":0.0,"z":0.0}},{"classname":"info_player_terrorist","origin":{"x":-384.0,"y":384.0,"z":-655.0},"angles":{"x":0.0,"y":0.0,"z":0.0}},{"classname":"info_player_terrorist","origin":{"x":-384.0,"y":448.0,"z":-655.0},"angles":{"x":0.0,"y":0.0,"z":0.0}},{"classname":"info_player_terrorist","origin":{"x":-320.0,"y":-448.0,"z":-655.0},"angles":{"x":0.0,"y":0.0,"z":0.0}},{"classname":"info_player_terrorist","origin":{"x":-320.0,"y":-384.0,"z":-655.0},"angles":{"x":0.0,"y":0.0,"z":0.0}},{"classname":"info_player_terrorist","origin":{"x":-320.0,"y":-320.0,"z":-655.0},"angles":{"x":0.0,"y":0.0,"z":0.0}},{"classname":"info_player_terrorist","origin":{"x":-320.0,"y":-256.0,"z":-655.0},"angles":{"x":0.0,"y":0.0,"z":0.0}},{"classname":"info_player_terrorist","origin":{"x":-320.0,"y":-192.0,"z":-655.0},"angles":{"x":0.0,"y":0.0,"z":0.0}},{"classname":"info_player_terrorist","origin":{"x":-320.0,"y":-128.0,"z":-655.0},"angles":{"x":0.0,"y":0.0,"z":0.0}},{"classname":"info_player_terrorist","origin":{"x":-320.0,"y":-64.0,"z":-655.0},"angles":{"x":0.0,"y":0.0,"z":0.0}},{"classname":"info_player_terrorist","origin":{"x":-320.0,"y":0.0,"z":-655.0},"angles":{"x":0.0,"y":0.0,"z":0.0}},{"classname":"info_player_terrorist","origin":{"x":-320.0,"y":64.0,"z":-655.0},"angles":{"x":0.0,"y":0.0,"z":0.0}},{"classname":"info_player_terrorist","origin":{"x":-320.0,"y":128.0,"z":-655.0},"angles":{"x":0.0,"y":0.0,"z":0.0}},{"classname":"info_player_terrorist","origin":{"x":-320.0,"y":192.0,"z":-655.0},"angles":{"x":0.0,"y":0.0,"z":0.0}},{"classname":"info_player_terrorist","origin":{"x":-320.0,"y":256.0,"z":-655.0},"angles":{"x":0.0,"y":0.0,"z":0.0}},{"classname":"info_player_terrorist","origin":{"x":-320.0,"y":320.0,"z":-655.0},"angles":{"x":0.0,"y":0.0,"z":0.0}},{"classname":"info_player_terrorist","origin":{"x":-320.0,"y":384.0,"z":-655.0},"angles":{"x":0.0,"y":0.0,"z":0.0}},{"classname":"info_player_terrorist","origin":{"x":-320.0,"y":448.0,"z":-655.0},"angles":{"x":0.0,"y":0.0,"z":0.0}},{"classname":"info_player_terrorist","origin":{"x":-256.0,"y":-448.0,"z":-655.0},"angles":{"x":0.0,"y":0.0,"z":0.0}},{"classname":"info_player_terrorist","origin":{"x":-256.0,"y":-384.0,"z":-655.0},"angles":{"x":0.0,"y":0.0,"z":0.0}},{"classname":"info_player_terrorist","origin":{"x":-256.0,"y":-320.0,"z":-655.0},"angles":{"x":0.0,"y":0.0,"z":0.0}},{"classname":"info_player_terrorist","origin":{"x":-256.0,"y":-256.0,"z":-655.0},"angles":{"x":0.0,"y":0.0,"z":0.0}},{"classname":"info_player_terrorist","origin":{"x":-256.0,"y":-192.0,"z":-655.0},"angles":{"x":0.0,"y":0.0,"z":0.0}},{"classname":"info_player_terrorist","origin":{"x":-256.0,"y":-128.0,"z":-655.0},"angles":{"x":0.0,"y":0.0,"z":0.0}},{"classname":"info_player_terrorist","origin":{"x":-256.0,"y":-64.0,"z":-655.0},"angles":{"x":0.0,"y":0.0,"z":0.0}},{"classname":"info_player_terrorist","origin":{"x":-256.0,"y":0.0,"z":-655.0},"angles":{"x":0.0,"y":0.0,"z":0.0}},{"classname":"info_player_terrorist","origin":{"x":-256.0,"y":64.0,"z":-655.0},"angles":{"x":0.0,"y":0.0,"z":0.0}},{"classname":"info_player_terrorist","origin":{"x":-256.0,"y":128.0,"z":-655.0},"angles":{"x":0.0,"y":0.0,"z":0.0}},{"classname":"info_player_terrorist","origin":{"x":-256.0,"y":192.0,"z":-655.0},"angles":{"x":0.0,"y":0.0,"z":0.0}},{"classname":"info_player_terrorist","origin":{"x":-256.0,"y":256.0,"z":-655.0},"angles":{"x":0.0,"y":0.0,"z":0.0}},{"classname":"info_player_terrorist","origin":{"x":-256.0,"y":320.0,"z":-655.0},"angles":{"x":0.0,"y":0.0,"z":0.0}},{"classname":"info_player_terrorist","origin":{"x":-256.0,"y":384.0,"z":-655.0},"angles":{"x":0.0,"y":0.0,"z":0.0}},{"classname":"info_player_terrorist","origin":{"x":-256.0,"y":448.0,"z":-655.0},"angles":{"x":0.0,"y":0.0,"z":0.0}},{"classname":"info_player_terrorist","origin":{"x":-192.0,"y":-448.0,"z":-655.0},"angles":{"x":0.0,"y":0.0,"z":0.0}},{"classname":"info_player_terrorist","origin":{"x":-192.0,"y":-384.0,"z":-655.0},"angles":{"x":0.0,"y":0.0,"z":0.0}},{"classname":"info_player_terrorist","origin":{"x":-192.0,"y":-320.0,"z":-655.0},"angles":{"x":0.0,"y":0.0,"z":0.0}},{"classname":"info_player_terrorist","origin":{"x":-192.0,"y":-256.0,"z":-655.0},"angles":{"x":0.0,"y":0.0,"z":0.0}},{"classname":"info_player_terrorist","origin":{"x":-192.0,"y":-192.0,"z":-655.0},"angles":{"x":0.0,"y":0.0,"z":0.0}},{"classname":"info_player_terrorist","origin":{"x":-192.0,"y":-128.0,"z":-655.0},"angles":{"x":0.0,"y":0.0,"z":0.0}},{"classname":"info_player_terrorist","origin":{"x":-192.0,"y":-64.0,"z":-655.0},"angles":{"x":0.0,"y":0.0,"z":0.0}},{"classname":"info_player_terrorist","origin":{"x":-192.0,"y":0.0,"z":-655.0},"angles":{"x":0.0,"y":0.0,"z":0.0}},{"classname":"info_player_terrorist","origin":{"x":-192.0,"y":64.0,"z":-655.0},"angles":{"x":0.0,"y":0.0,"z":0.0}},{"classname":"info_player_terrorist","origin":{"x":-192.0,"y":128.0,"z":-655.0},"angles":{"x":0.0,"y":0.0,"z":0.0}},{"classname":"info_player_terrorist","origin":{"x":-192.0,"y":192.0,"z":-655.0},"angles":{"x":0.0,"y":0.0,"z":0.0}},{"classname":"info_player_terrorist","origin":{"x":-192.0,"y":256.0,"z":-655.0},"angles":{"x":0.0,"y":0.0,"z":0.0}},{"classname":"info_player_terrorist","origin":{"x":-192.0,"y":320.0,"z":-655.0},"angles":{"x":0.0,"y":0.0,"z":0.0}},{"classname":"info_player_terrorist","origin":{"x":-192.0,"y":384.0,"z":-655.0},"angles":{"x":0.0,"y":0.0,"z":0.0}},{"classname":"info_player_terrorist","origin":{"x":-192.0,"y":448.0,"z":-655.0},"angles":{"x":0.0,"y":0.0,"z":0.0}},{"classname":"info_player_terrorist","origin":{"x":-128.0,"y":-448.0,"z":-655.0},"angles":{"x":0.0,"y":0.0,"z":0.0}},{"classname":"info_player_terrorist","origin":{"x":-128.0,"y":-384.0,"z":-655.0},"angles":{"x":0.0,"y":0.0,"z":0.0}},{"classname":"info_player_terrorist","origin":{"x":-128.0,"y":-320.0,"z":-655.0},"angles":{"x":0.0,"y":0.0,"z":0.0}},{"classname":"info_player_terrorist","origin":{"x":-128.0,"y":-256.0,"z":-655.0},"angles":{"x":0.0,"y":0.0,"z":0.0}},{"classname":"info_player_terrorist","origin":{"x":-128.0,"y":-192.0,"z":-655.0},"angles":{"x":0.0,"y":0.0,"z":0.0}},{"classname":"info_player_terrorist","origin":{"x":-128.0,"y":-128.0,"z":-655.0},"angles":{"x":0.0,"y":0.0,"z":0.0}},{"classname":"info_player_terrorist","origin":{"x":-128.0,"y":-64.0,"z":-655.0},"angles":{"x":0.0,"y":0.0,"z":0.0}},{"classname":"info_player_terrorist","origin":{"x":-128.0,"y":0.0,"z":-655.0},"angles":{"x":0.0,"y":0.0,"z":0.0}},{"classname":"info_player_terrorist","origin":{"x":-128.0,"y":64.0,"z":-655.0},"angles":{"x":0.0,"y":0.0,"z":0.0}},{"classname":"info_player_terrorist","origin":{"x":-128.0,"y":128.0,"z":-655.0},"angles":{"x":0.0,"y":0.0,"z":0.0}},{"classname":"info_player_terrorist","origin":{"x":-128.0,"y":192.0,"z":-655.0},"angles":{"x":0.0,"y":0.0,"z":0.0}},{"classname":"info_player_terrorist","origin":{"x":-128.0,"y":256.0,"z":-655.0},"angles":{"x":0.0,"y":0.0,"z":0.0}},{"classname":"info_player_terrorist","origin":{"x":-128.0,"y":320.0,"z":-655.0},"angles":{"x":0.0,"y":0.0,"z":0.0}},{"classname":"info_player_terrorist","origin":{"x":-128.0,"y":384.0,"z":-655.0},"angles":{"x":0.0,"y":0.0,"z":0.0}},{"classname":"info_player_terrorist","origin":{"x":-128.0,"y":448.0,"z":-655.0},"angles":{"x":0.0,"y":0.0,"z":0.0}},{"classname":"info_player_terrorist","origin":{"x":-64.0,"y":-448.0,"z":-655.0},"angles":{"x":0.0,"y":0.0,"z":0.0}},{"classname":"info_player_terrorist","origin":{"x":-64.0,"y":-384.0,"z":-655.0},"angles":{"x":0.0,"y":0.0,"z":0.0}},{"classname":"info_player_terrorist","origin":{"x":-64.0,"y":-320.0,"z":-655.0},"angles":{"x":0.0,"y":0.0,"z":0.0}},{"classname":"info_player_terrorist","origin":{"x":-64.0,"y":-256.0,"z":-655.0},"angles":{"x":0.0,"y":0.0,"z":0.0}},{"classname":"info_player_terrorist","origin":{"x":-64.0,"y":-192.0,"z":-655.0},"angles":{"x":0.0,"y":0.0,"z":0.0}},{"classname":"info_player_terrorist","origin":{"x":-64.0,"y":-128.0,"z":-655.0},"angles":{"x":0.0,"y":0.0,"z":0.0}},{"classname":"info_player_terrorist","origin":{"x":-64.0,"y":-64.0,"z":-655.0},"angles":{"x":0.0,"y":0.0,"z":0.0}},{"classname":"info_player_terrorist","origin":{"x":-64.0,"y":0.0,"z":-655.0},"angles":{"x":0.0,"y":0.0,"z":0.0}},{"classname":"info_player_terrorist","origin":{"x":-64.0,"y":64.0,"z":-655.0},"angles":{"x":0.0,"y":0.0,"z":0.0}},{"classname":"info_player_terrorist","origin":{"x":-64.0,"y":128.0,"z":-655.0},"angles":{"x":0.0,"y":0.0,"z":0.0}},{"classname":"info_player_terrorist","origin":{"x":-64.0,"y":192.0,"z":-655.0},"angles":{"x":0.0,"y":0.0,"z":0.0}},{"classname":"info_player_terrorist","origin":{"x":-64.0,"y":256.0,"z":-655.0},"angles":{"x":0.0,"y":0.0,"z":0.0}},{"classname":"info_player_terrorist","origin":{"x":-64.0,"y":320.0,"z":-655.0},"angles":{"x":0.0,"y":0.0,"z":0.0}},{"classname":"info_player_terrorist","origin":{"x":-64.0,"y":384.0,"z":-655.0},"angles":{"x":0.0,"y":0.0,"z":0.0}},{"classname":"info_player_terrorist","origin":{"x":-64.0,"y":448.0,"z":-655.0},"angles":{"x":0.0,"y":0.0,"z":0.0}},{"classname":"info_player_terrorist","origin":{"x":0.0,"y":-448.0,"z":-655.0},"angles":{"x":0.0,"y":0.0,"z":0.0}},{"classname":"info_player_terrorist","origin":{"x":0.0,"y":-384.0,"z":-655.0},"angles":{"x":0.0,"y":0.0,"z":0.0}},{"classname":"info_player_terrorist","origin":{"x":0.0,"y":-320.0,"z":-655.0},"angles":{"x":0.0,"y":0.0,"z":0.0}},{"classname":"info_player_terrorist","origin":{"x":0.0,"y":-256.0,"z":-655.0},"angles":{"x":0.0,"y":0.0,"z":0.0}},{"classname":"info_player_terrorist","origin":{"x":0.0,"y":-192.0,"z":-655.0},"angles":{"x":0.0,"y":0.0,"z":0.0}},{"classname":"info_player_terrorist","origin":{"x":0.0,"y":-128.0,"z":-655.0},"angles":{"x":0.0,"y":0.0,"z":0.0}},{"classname":"info_player_terrorist","origin":{"x":0.0,"y":-64.0,"z":-655.0},"angles":{"x":0.0,"y":0.0,"z":0.0}},{"classname":"info_player_terrorist","origin":{"x":0.0,"y":0.0,"z":-655.0},"angles":{"x":0.0,"y":0.0,"z":0.0}},{"classname":"info_player_terrorist","origin":{"x":0.0,"y":64.0,"z":-655.0},"angles":{"x":0.0,"y":0.0,"z":0.0}},{"classname":"info_player_terrorist","origin":{"x":0.0,"y":128.0,"z":-655.0},"angles":{"x":0.0,"y":0.0,"z":0.0}},{"classname":"info_player_terrorist","origin":{"x":0.0,"y":192.0,"z":-655.0},"angles":{"x":0.0,"y":0.0,"z":0.0}},{"classname":"info_player_terrorist","origin":{"x":0.0,"y":256.0,"z":-655.0},"angles":{"x":0.0,"y":0.0,"z":0.0}},{"classname":"info_player_terrorist","origin":{"x":0.0,"y":320.0,"z":-655.0},"angles":{"x":0.0,"y":0.0,"z":0.0}},{"classname":"info_player_terrorist","origin":{"x":0.0,"y":384.0,"z":-655.0},"angles":{"x":0.0,"y":0.0,"z":0.0}},{"classname":"info_player_terrorist","origin":{"x":0.0,"y":448.0,"z":-655.0},"angles":{"x":0.0,"y":0.0,"z":0.0}},{"classname":"info_player_terrorist","origin":{"x":64.0,"y":-448.0,"z":-655.0},"angles":{"x":0.0,"y":0.0,"z":0.0}},{"classname":"info_player_terrorist","origin":{"x":64.0,"y":-384.0,"z":-655.0},"angles":{"x":0.0,"y":0.0,"z":0.0}},{"classname":"info_player_terrorist","origin":{"x":64.0,"y":-320.0,"z":-655.0},"angles":{"x":0.0,"y":0.0,"z":0.0}},{"classname":"info_player_terrorist","origin":{"x":64.0,"y":-256.0,"z":-655.0},"angles":{"x":0.0,"y":0.0,"z":0.0}},{"classname":"info_player_terrorist","origin":{"x":64.0,"y":-192.0,"z":-655.0},"angles":{"x":0.0,"y":0.0,"z":0.0}},{"classname":"info_player_terrorist","origin":{"x":64.0,"y":-128.0,"z":-655.0},"angles":{"x":0.0,"y":0.0,"z":0.0}},{"classname":"info_player_terrorist","origin":{"x":64.0,"y":-64.0,"z":-655.0},"angles":{"x":0.0,"y":0.0,"z":0.0}},{"classname":"info_player_terrorist","origin":{"x":64.0,"y":0.0,"z":-655.0},"angles":{"x":0.0,"y":0.0,"z":0.0}},{"classname":"info_player_terrorist","origin":{"x":64.0,"y":64.0,"z":-655.0},"angles":{"x":0.0,"y":0.0,"z":0.0}},{"classname":"info_player_terrorist","origin":{"x":64.0,"y":128.0,"z":-655.0},"angles":{"x":0.0,"y":0.0,"z":0.0}},{"classname":"info_player_terrorist","origin":{"x":64.0,"y":192.0,"z":-655.0},"angles":{"x":0.0,"y":0.0,"z":0.0}},{"classname":"info_player_terrorist","origin":{"x":64.0,"y":256.0,"z":-655.0},"angles":{"x":0.0,"y":0.0,"z":0.0}},{"classname":"info_player_terrorist","origin":{"x":64.0,"y":320.0,"z":-655.0},"angles":{"x":0.0,"y":0.0,"z":0.0}},{"classname":"info_player_terrorist","origin":{"x":64.0,"y":384.0,"z":-655.0},"angles":{"x":0.0,"y":0.0,"z":0.0}},{"classname":"info_player_terrorist","origin":{"x":64.0,"y":448.0,"z":-655.0},"angles":{"x":0.0,"y":0.0,"z":0.0}},{"classname":"info_player_terrorist","origin":{"x":128.0,"y":-448.0,"z":-655.0},"angles":{"x":0.0,"y":0.0,"z":0.0}},{"classname":"info_player_terrorist","origin":{"x":128.0,"y":-384.0,"z":-655.0},"angles":{"x":0.0,"y":0.0,"z":0.0}},{"classname":"info_player_terrorist","origin":{"x":128.0,"y":-320.0,"z":-655.0},"angles":{"x":0.0,"y":0.0,"z":0.0}},{"classname":"info_player_terrorist","origin":{"x":128.0,"y":-256.0,"z":-655.0},"angles":{"x":0.0,"y":0.0,"z":0.0}},{"classname":"info_player_terrorist","origin":{"x":128.0,"y":-192.0,"z":-655.0},"angles":{"x":0.0,"y":0.0,"z":0.0}},{"classname":"info_player_terrorist","origin":{"x":128.0,"y":-128.0,"z":-655.0},"angles":{"x":0.0,"y":0.0,"z":0.0}},{"classname":"info_player_terrorist","origin":{"x":128.0,"y":-64.0,"z":-655.0},"angles":{"x":0.0,"y":0.0,"z":0.0}},{"classname":"info_player_terrorist","origin":{"x":128.0,"y":0.0,"z":-655.0},"angles":{"x":0.0,"y":0.0,"z":0.0}},{"classname":"info_player_terrorist","origin":{"x":128.0,"y":64.0,"z":-655.0},"angles":{"x":0.0,"y":0.0,"z":0.0}},{"classname":"info_player_terrorist","origin":{"x":128.0,"y":128.0,"z":-655.0},"angles":{"x":0.0,"y":0.0,"z":0.0}},{"classname":"info_player_terrorist","origin":{"x":128.0,"y":192.0,"z":-655.0},"angles":{"x":0.0,"y":0.0,"z":0.0}},{"classname":"info_player_terrorist","origin":{"x":128.0,"y":256.0,"z":-655.0},"angles":{"x":0.0,"y":0.0,"z":0.0}},{"classname":"info_player_terrorist","origin":{"x":128.0,"y":320.0,"z":-655.0},"angles":{"x":0.0,"y":0.0,"z":0.0}},{"classname":"info_player_terrorist","origin":{"x":128.0,"y":384.0,"z":-655.0},"angles":{"x":0.0,"y":0.0,"z":0.0}},{"classname":"info_player_terrorist","origin":{"x":128.0,"y":448.0,"z":-655.0},"angles":{"x":0.0,"y":0.0,"z":0.0}},{"classname":"info_player_terrorist","origin":{"x":192.0,"y":-448.0,"z":-655.0},"angles":{"x":0.0,"y":0.0,"z":0.0}},{"classname":"info_player_terrorist","origin":{"x":192.0,"y":-384.0,"z":-655.0},"angles":{"x":0.0,"y":0.0,"z":0.0}},{"classname":"info_player_terrorist","origin":{"x":192.0,"y":-320.0,"z":-655.0},"angles":{"x":0.0,"y":0.0,"z":0.0}},{"classname":"info_player_terrorist","origin":{"x":192.0,"y":-256.0,"z":-655.0},"angles":{"x":0.0,"y":0.0,"z":0.0}},{"classname":"info_player_terrorist","origin":{"x":192.0,"y":-192.0,"z":-655.0},"angles":{"x":0.0,"y":0.0,"z":0.0}},{"classname":"info_player_terrorist","origin":{"x":192.0,"y":-128.0,"z":-655.0},"angles":{"x":0.0,"y":0.0,"z":0.0}},{"classname":"info_player_terrorist","origin":{"x":192.0,"y":-64.0,"z":-655.0},"angles":{"x":0.0,"y":0.0,"z":0.0}},{"classname":"info_player_terrorist","origin":{"x":192.0,"y":0.0,"z":-655.0},"angles":{"x":0.0,"y":0.0,"z":0.0}},{"classname":"info_player_terrorist","origin":{"x":192.0,"y":64.0,"z":-655.0},"angles":{"x":0.0,"y":0.0,"z":0.0}},{"classname":"info_player_terrorist","origin":{"x":192.0,"y":128.0,"z":-655.0},"angles":{"x":0.0,"y":0.0,"z":0.0}},{"classname":"info_player_terrorist","origin":{"x":192.0,"y":192.0,"z":-655.0},"angles":{"x":0.0,"y":0.0,"z":0.0}},{"classname":"info_player_terrorist","origin":{"x":192.0,"y":256.0,"z":-655.0},"angles":{"x":0.0,"y":0.0,"z":0.0}},{"classname":"info_player_terrorist","origin":{"x":192.0,"y":320.0,"z":-655.0},"angles":{"x":0.0,"y":0.0,"z":0.0}},{"classname":"info_player_terrorist","origin":{"x":192.0,"y":384.0,"z":-655.0},"angles":{"x":0.0,"y":0.0,"z":0.0}},{"classname":"info_player_terrorist","origin":{"x":192.0,"y":448.0,"z":-655.0},"angles":{"x":0.0,"y":0.0,"z":0.0}},{"classname":"info_player_terrorist","origin":{"x":256.0,"y":-448.0,"z":-655.0},"angles":{"x":0.0,"y":0.0,"z":0.0}},{"classname":"info_player_terrorist","origin":{"x":256.0,"y":-384.0,"z":-655.0},"angles":{"x":0.0,"y":0.0,"z":0.0}},{"classname":"info_player_terrorist","origin":{"x":256.0,"y":-320.0,"z":-655.0},"angles":{"x":0.0,"y":0.0,"z":0.0}},{"classname":"info_player_terrorist","origin":{"x":256.0,"y":-256.0,"z":-655.0},"angles":{"x":0.0,"y":0.0,"z":0.0}},{"classname":"info_player_terrorist","origin":{"x":256.0,"y":-192.0,"z":-655.0},"angles":{"x":0.0,"y":0.0,"z":0.0}},{"classname":"info_player_terrorist","origin":{"x":256.0,"y":-128.0,"z":-655.0},"angles":{"x":0.0,"y":0.0,"z":0.0}},{"classname":"info_player_terrorist","origin":{"x":256.0,"y":-64.0,"z":-655.0},"angles":{"x":0.0,"y":0.0,"z":0.0}},{"classname":"info_player_terrorist","origin":{"x":256.0,"y":0.0,"z":-655.0},"angles":{"x":0.0,"y":0.0,"z":0.0}},{"classname":"info_player_terrorist","origin":{"x":256.0,"y":64.0,"z":-655.0},"angles":{"x":0.0,"y":0.0,"z":0.0}},{"classname":"info_player_terrorist","origin":{"x":256.0,"y":128.0,"z":-655.0},"angles":{"x":0.0,"y":0.0,"z":0.0}},{"classname":"info_player_terrorist","origin":{"x":256.0,"y":192.0,"z":-655.0},"angles":{"x":0.0,"y":0.0,"z":0.0}},{"classname":"info_player_terrorist","origin":{"x":256.0,"y":256.0,"z":-655.0},"angles":{"x":0.0,"y":0.0,"z":0.0}},{"classname":"info_player_terrorist","origin":{"x":256.0,"y":320.0,"z":-655.0},"angles":{"x":0.0,"y":0.0,"z":0.0}},{"classname":"info_player_terrorist","origin":{"x":256.0,"y":384.0,"z":-655.0},"angles":{"x":0.0,"y":0.0,"z":0.0}},{"classname":"info_player_terrorist","origin":{"x":256.0,"y":448.0,"z":-655.0},"angles":{"x":0.0,"y":0.0,"z":0.0}},{"classname":"info_player_terrorist","origin":{"x":320.0,"y":-448.0,"z":-655.0},"angles":{"x":0.0,"y":0.0,"z":0.0}},{"classname":"info_player_terrorist","origin":{"x":320.0,"y":-384.0,"z":-655.0},"angles":{"x":0.0,"y":0.0,"z":0.0}},{"classname":"info_player_terrorist","origin":{"x":320.0,"y":-320.0,"z":-655.0},"angles":{"x":0.0,"y":0.0,"z":0.0}},{"classname":"info_player_terrorist","origin":{"x":320.0,"y":-256.0,"z":-655.0},"angles":{"x":0.0,"y":0.0,"z":0.0}},{"classname":"info_player_terrorist","origin":{"x":320.0,"y":-192.0,"z":-655.0},"angles":{"x":0.0,"y":0.0,"z":0.0}},{"classname":"info_player_terrorist","origin":{"x":320.0,"y":-128.0,"z":-655.0},"angles":{"x":0.0,"y":0.0,"z":0.0}},{"classname":"info_player_terrorist","origin":{"x":320.0,"y":-64.0,"z":-655.0},"angles":{"x":0.0,"y":0.0,"z":0.0}},{"classname":"info_player_terrorist","origin":{"x":320.0,"y":0.0,"z":-655.0},"angles":{"x":0.0,"y":0.0,"z":0.0}},{"classname":"info_player_terrorist","origin":{"x":320.0,"y":64.0,"z":-655.0},"angles":{"x":0.0,"y":0.0,"z":0.0}},{"classname":"info_player_terrorist","origin":{"x":320.0,"y":128.0,"z":-655.0},"angles":{"x":0.0,"y":0.0,"z":0.0}},{"classname":"info_player_terrorist","origin":{"x":320.0,"y":192.0,"z":-655.0},"angles":{"x":0.0,"y":0.0,"z":0.0}},{"classname":"info_player_terrorist","origin":{"x":320.0,"y":256.0,"z":-655.0},"angles":{"x":0.0,"y":0.0,"z":0.0}},{"classname":"info_player_terrorist","origin":{"x":320.0,"y":320.0,"z":-655.0},"angles":{"x":0.0,"y":0.0,"z":0.0}},{"classname":"info_player_terrorist","origin":{"x":320.0,"y":384.0,"z":-655.0},"angles":{"x":0.0,"y":0.0,"z":0.0}},{"classname":"info_player_terrorist","origin":{"x":320.0,"y":448.0,"z":-655.0},"angles":{"x":0.0,"y":0.0,"z":0.0}},{"classname":"info_player_terrorist","origin":{"x":384.0,"y":-448.0,"z":-655.0},"angles":{"x":0.0,"y":0.0,"z":0.0}},{"classname":"info_player_terrorist","origin":{"x":384.0,"y":-384.0,"z":-655.0},"angles":{"x":0.0,"y":0.0,"z":0.0}},{"classname":"info_player_terrorist","origin":{"x":384.0,"y":-320.0,"z":-655.0},"angles":{"x":0.0,"y":0.0,"z":0.0}},{"classname":"info_player_terrorist","origin":{"x":384.0,"y":-256.0,"z":-655.0},"angles":{"x":0.0,"y":0.0,"z":0.0}},{"classname":"info_player_terrorist","origin":{"x":384.0,"y":-192.0,"z":-655.0},"angles":{"x":0.0,"y":0.0,"z":0.0}},{"classname":"info_player_terrorist","origin":{"x":384.0,"y":-128.0,"z":-655.0},"angles":{"x":0.0,"y":0.0,"z":0.0}},{"classname":"info_player_terrorist","origin":{"x":384.0,"y":-64.0,"z":-655.0},"angles":{"x":0.0,"y":0.0,"z":0.0}},{"classname":"info_player_terrorist","origin":{"x":384.0,"y":0.0,"z":-655.0},"angles":{"x":0.0,"y":0.0,"z":0.0}},{"classname":"info_player_terrorist","origin":{"x":384.0,"y":64.0,"z":-655.0},"angles":{"x":0.0,"y":0.0,"z":0.0}},{"classname":"info_player_terrorist","origin":{"x":384.0,"y":128.0,"z":-655.0},"angles":{"x":0.0,"y":0.0,"z":0.0}},{"classname":"info_player_terrorist","origin":{"x":384.0,"y":192.0,"z":-655.0},"angles":{"x":0.0,"y":0.0,"z":0.0}},{"classname":"info_player_terrorist","origin":{"x":384.0,"y":256.0,"z":-655.0},"angles":{"x":0.0,"y":0.0,"z":0.0}},{"classname":"info_player_terrorist","origin":{"x":384.0,"y":320.0,"z":-655.0},"angles":{"x":0.0,"y":0.0,"z":0.0}},{"classname":"info_player_terrorist","origin":{"x":384.0,"y":384.0,"z":-655.0},"angles":{"x":0.0,"y":0.0,"z":0.0}},{"classname":"info_player_terrorist","origin":{"x":384.0,"y":448.0,"z":-655.0},"angles":{"x":0.0,"y":0.0,"z":0.0}},{"classname":"info_player_terrorist","origin":{"x":448.0,"y":-448.0,"z":-655.0},"angles":{"x":0.0,"y":0.0,"z":0.0}},{"classname":"info_player_terrorist","origin":{"x":448.0,"y":-384.0,"z":-655.0},"angles":{"x":0.0,"y":0.0,"z":0.0}},{"classname":"info_player_terrorist","origin":{"x":448.0,"y":-320.0,"z":-655.0},"angles":{"x":0.0,"y":0.0,"z":0.0}},{"classname":"info_player_terrorist","origin":{"x":448.0,"y":-256.0,"z":-655.0},"angles":{"x":0.0,"y":0.0,"z":0.0}},{"classname":"info_player_terrorist","origin":{"x":448.0,"y":-192.0,"z":-655.0},"angles":{"x":0.0,"y":0.0,"z":0.0}},{"classname":"info_player_terrorist","origin":{"x":448.0,"y":-128.0,"z":-655.0},"angles":{"x":0.0,"y":0.0,"z":0.0}},{"classname":"info_player_terrorist","origin":{"x":448.0,"y":-64.0,"z":-655.0},"angles":{"x":0.0,"y":0.0,"z":0.0}},{"classname":"info_player_terrorist","origin":{"x":448.0,"y":0.0,"z":-655.0},"angles":{"x":0.0,"y":0.0,"z":0.0}},{"classname":"info_player_terrorist","origin":{"x":448.0,"y":64.0,"z":-655.0},"angles":{"x":0.0,"y":0.0,"z":0.0}},{"classname":"info_player_terrorist","origin":{"x":448.0,"y":128.0,"z":-655.0},"angles":{"x":0.0,"y":0.0,"z":0.0}},{"classname":"info_player_terrorist","origin":{"x":448.0,"y":192.0,"z":-655.0},"angles":{"x":0.0,"y":0.0,"z":0.0}},{"classname":"info_player_terrorist","origin":{"x":448.0,"y":256.0,"z":-655.0},"angles":{"x":0.0,"y":0.0,"z":0.0}},{"classname":"info_player_terrorist","origin":{"x":448.0,"y":320.0,"z":-655.0},"angles":{"x":0.0,"y":0.0,"z":0.0}},{"classname":"info_player_terrorist","origin":{"x":448.0,"y":384.0,"z":-655.0},"angles":{"x":0.0,"y":0.0,"z":0.0}},{"classname":"info_player_terrorist","origin":{"x":448.0,"y":448.0,"z":-655.0},"angles":{"x":0.0,"y":0.0,"z":0.0}},{"classname":"trigger_teleport","origin":{"x":0.0,"y":0.0,"z":-655.5}},{"targetname":"spawnroom","classname":"info_teleport_destination","origin":{"x":0.0,"y":832.0,"z":-1840.0},"angles":{"x":0.0,"y":270.0,"z":0.0}},{"model":89,"clusters":[1157,1158,1159,1160,1161,1162,1163,1164,1165,1166,1167,1168,1172,1173,1174,1177,1178,1179,2334,2335,2336,2337,2338,2339,2340,2341,2342,2343,2347,2348,2349,2350,2351,2354,2355,2356],"classname":"func_brush","origin":{"x":0.0,"y":544.0,"z":-1848.0}},{"model":90,"clusters":[3717,3718,3722,3723,3724,3725,3726,3727,3728,3729,3730,3731,3736,3737,3738,3739,3740,3743,4507,4508,4509,4510,4511,4512,4513,4514,4515,4516,4517,4518,4523,4524,4525,4526,4527,4530],"classname":"func_brush","origin":{"x":0.0,"y":-544.0,"z":-1848.0}},{"classname":"point_viewcontrol","origin":{"x":-448.0,"y":-448.0,"z":-864.0},"angles":{"x":0.0,"y":0.0,"z":0.0}},{"targetname":"viewtarget","classname":"info_target","origin":{"x":0.0,"y":0.0,"z":-1424.0},"angles":{"x":0.0,"y":0.0,"z":0.0}},{"classname":"light","origin":{"x":0.0,"y":0.0,"z":-1192.0}},{"classname":"env_lightglow","origin":{"x":0.0,"y":0.0,"z":-1192.0},"angles":{"x":0.0,"y":0.0,"z":0.0}},{"targetname":"essence_tesla","classname":"point_tesla","origin":{"x":0.0,"y":0.0,"z":-1192.0}},{"classname":"logic_auto","origin":{"x":0.0,"y":0.0,"z":-1224.0}},{"classname":"env_spritetrail","origin":{"x":20.0,"y":0.0,"z":-1392.0}},{"classname":"env_spritetrail","origin":{"x":-20.0,"y":0.0,"z":-1392.0}},{"targetname":"spawn_rotate1","classname":"func_rotating","origin":{"x":0.0,"y":0.0,"z":-1392.0},"angles":{"x":0.0,"y":0.0,"z":0.0}},{"classname":"env_spritetrail","origin":{"x":0.0,"y":-20.0,"z":-1360.0}},{"classname":"env_spritetrail","origin":{"x":0.0,"y":20.0,"z":-1360.0}},{"classname":"env_spritetrail","origin":{"x":-20.0,"y":0.0,"z":-1328.0}},{"classname":"env_spritetrail","origin":{"x":20.0,"y":0.0,"z":-1328.0}},{"classname":"env_spritetrail","origin":{"x":0.0,"y":-20.0,"z":-1296.0}},{"classname":"env_spritetrail","origin":{"x":0.0,"y":20.0,"z":-1296.0}},{"classname":"env_spritetrail","origin":{"x":-20.0,"y":0.0,"z":-1264.0}},{"classname":"env_spritetrail","origin":{"x":20.0,"y":0.0,"z":-1264.0}},{"classname":"env_spritetrail","origin":{"x":0.0,"y":-20.0,"z":-1424.0}},{"classname":"env_spritetrail","origin":{"x":0.0,"y":20.0,"z":-1424.0}},{"Brightness":{"R":255,"G":255,"B":255,"A":200},"Ambient":{"R":255,"G":255,"B":255,"A":20},"BrightnessHdr":{"R":255,"G":255,"B":255,"A":1},"AmbientHdr":{"R":255,"G":255,"B":255,"A":1},"BrightnessScaleHdr":1.0,"AmbientScaleHdr":1.0,"Pitch":-62.0,"classname":"light_environment","origin":{"x":-2784.0,"y":-1856.0,"z":1344.0},"angles":{"x":-62.0,"y":123.0,"z":0.0}},{"classname":"light","origin":{"x":-3040.0,"y":-1600.0,"z":1344.0}},{"classname":"light","origin":{"x":-2528.0,"y":-1600.0,"z":1344.0}},{"classname":"light","origin":{"x":-2528.0,"y":-2112.0,"z":1344.0}},{"classname":"light","origin":{"x":-3040.0,"y":-2112.0,"z":1344.0}},{"classname":"light","origin":{"x":-2816.0,"y":-1824.0,"z":1104.0}},{"classname":"light","origin":{"x":-2752.0,"y":-1824.0,"z":1104.0}},{"classname":"light","origin":{"x":-2752.0,"y":-1888.0,"z":1104.0}},{"classname":"light","origin":{"x":-2816.0,"y":-1888.0,"z":1104.0}},{"classname":"light","origin":{"x":-2816.0,"y":-1888.0,"z":1040.0}},{"classname":"light","origin":{"x":-2816.0,"y":-1824.0,"z":1040.0}},{"classname":"light","origin":{"x":-2752.0,"y":-1824.0,"z":1040.0}},{"classname":"light","origin":{"x":-2752.0,"y":-1888.0,"z":1040.0}},{"classname":"light","origin":{"x":-2816.0,"y":-1888.0,"z":976.0}},{"classname":"light","origin":{"x":-2816.0,"y":-1824.0,"z":976.0}},{"classname":"light","origin":{"x":-2752.0,"y":-1824.0,"z":976.0}},{"classname":"light","origin":{"x":-2752.0,"y":-1888.0,"z":976.0}},{"classname":"light","origin":{"x":-2816.0,"y":-1888.0,"z":912.0}},{"classname":"light","origin":{"x":-2816.0,"y":-1824.0,"z":912.0}},{"classname":"light","origin":{"x":-2752.0,"y":-1824.0,"z":912.0}},{"classname":"light","origin":{"x":-2752.0,"y":-1888.0,"z":912.0}},{"classname":"light","origin":{"x":-2816.0,"y":-1888.0,"z":848.0}},{"classname":"light","origin":{"x":-2816.0,"y":-1824.0,"z":848.0}},{"classname":"light","origin":{"x":-2752.0,"y":-1824.0,"z":848.0}},{"classname":"light","origin":{"x":-2752.0,"y":-1888.0,"z":848.0}},{"classname":"light","origin":{"x":-2816.0,"y":-1888.0,"z":784.0}},{"classname":"light","origin":{"x":-2816.0,"y":-1824.0,"z":784.0}},{"classname":"light","origin":{"x":-2752.0,"y":-1824.0,"z":784.0}},{"classname":"light","origin":{"x":-2752.0,"y":-1888.0,"z":784.0}},{"classname":"light","origin":{"x":-2816.0,"y":-1888.0,"z":720.0}},{"classname":"light","origin":{"x":-2816.0,"y":-1824.0,"z":720.0}},{"classname":"light","origin":{"x":-2752.0,"y":-1824.0,"z":720.0}},{"classname":"light","origin":{"x":-2752.0,"y":-1888.0,"z":720.0}},{"targetname":"endroom","classname":"info_teleport_destination","origin":{"x":-2784.0,"y":-2240.0,"z":1400.0},"angles":{"x":0.0,"y":90.0,"z":0.0}},{"classname":"light","origin":{"x":-2784.0,"y":-2240.0,"z":1312.0}},{"classname":"light","origin":{"x":-2784.0,"y":-2240.0,"z":1344.0}},{"classname":"light","origin":{"x":-2784.0,"y":-2240.0,"z":1376.0}},{"classname":"light","origin":{"x":-2784.0,"y":-2240.0,"z":1408.0}},{"classname":"light","origin":{"x":-2784.0,"y":-2240.0,"z":1440.0}},{"classname":"light","origin":{"x":-2784.0,"y":-2240.0,"z":1472.0}},{"classname":"light","origin":{"x":-2784.0,"y":-2240.0,"z":1280.0}},{"classname":"light","origin":{"x":-2784.0,"y":-2240.0,"z":1248.0}},{"classname":"light","origin":{"x":-2784.0,"y":-2240.0,"z":1216.0}},{"classname":"trigger_teleport","origin":{"x":-2308.0,"y":-1856.0,"z":1328.0}},{"classname":"trigger_teleport","origin":{"x":13232.0,"y":-14336.0,"z":928.0}},{"classname":"trigger_teleport","origin":{"x":15440.0,"y":-14336.0,"z":928.0}},{"classname":"trigger_teleport","origin":{"x":14336.0,"y":-13232.0,"z":928.0}},{"classname":"trigger_teleport","origin":{"x":14336.0,"y":-15440.0,"z":928.0}},{"classname":"trigger_teleport","origin":{"x":10240.0,"y":3568.0,"z":-5856.0}},{"targetname":"stage4","classname":"trigger_multiple","origin":{"x":-10560.0,"y":14784.0,"z":1756.0}},{"targetname":"dmg","classname":"filter_damage_type","origin":{"x":-10560.0,"y":14784.0,"z":1728.0}},{"classname":"trigger_teleport","origin":{"x":-8608.0,"y":14784.0,"z":-1022.0}},{"classname":"trigger_teleport","origin":{"x":-4832.0,"y":14784.0,"z":-1022.0}},{"classname":"trigger_teleport","origin":{"x":-9504.0,"y":14784.0,"z":-3070.0}},{"classname":"trigger_teleport","origin":{"x":-5218.0,"y":14784.0,"z":-606.0}},{"classname":"trigger_teleport","origin":{"x":-5248.0,"y":14784.0,"z":-9726.0}},{"classname":"trigger_teleport","origin":{"x":-8128.0,"y":14784.0,"z":-9214.0}},{"classname":"trigger_teleport","origin":{"x":-2591.93,"y":14784.0,"z":-12734.0}},{"targetname":"essence_stage6","classname":"info_teleport_destination","origin":{"x":-10560.0,"y":14784.0,"z":1664.0},"angles":{"x":0.0,"y":0.0,"z":0.0}},{"Brightness":{"R":255,"G":255,"B":255,"A":200},"Ambient":{"R":255,"G":255,"B":255,"A":20},"BrightnessHdr":{"R":255,"G":255,"B":255,"A":1},"AmbientHdr":{"R":255,"G":255,"B":255,"A":1},"BrightnessScaleHdr":1.0,"AmbientScaleHdr":1.0,"Pitch":-30.0,"classname":"light_environment","origin":{"x":-7872.0,"y":14784.0,"z":64.0},"angles":{"x":-30.0,"y":220.0,"z":0.0}},{"classname":"trigger_teleport","origin":{"x":-6784.0,"y":14784.0,"z":-9726.0}},{"classname":"trigger_teleport","origin":{"x":-14848.0,"y":14304.0,"z":-3070.0}},{"classname":"trigger_teleport","origin":{"x":-14368.0,"y":14784.0,"z":-3582.0}},{"classname":"trigger_teleport","origin":{"x":-14848.0,"y":15264.0,"z":-4094.0}},{"classname":"trigger_teleport","origin":{"x":-15328.0,"y":14784.0,"z":-4606.0}},{"classname":"trigger_teleport","origin":{"x":-15328.0,"y":14784.0,"z":-6654.0}},{"classname":"trigger_teleport","origin":{"x":-14848.0,"y":15264.0,"z":-6142.0}},{"classname":"trigger_teleport","origin":{"x":-14368.0,"y":14784.0,"z":-5630.0}},{"classname":"trigger_teleport","origin":{"x":-14848.0,"y":14304.0,"z":-5118.0}},{"classname":"light","origin":{"x":-14848.0,"y":14784.0,"z":-2816.0}},{"classname":"light","origin":{"x":-14848.0,"y":14784.0,"z":-3328.0}},{"classname":"light","origin":{"x":-14848.0,"y":14784.0,"z":-3904.0}},{"classname":"light","origin":{"x":-14848.0,"y":14784.0,"z":-4416.0}},{"classname":"light","origin":{"x":-14848.0,"y":14784.0,"z":-4928.0}},{"classname":"light","origin":{"x":-14848.0,"y":14784.0,"z":-5440.0}},{"classname":"light","origin":{"x":-14848.0,"y":14784.0,"z":-5888.0}},{"classname":"light","origin":{"x":-14848.0,"y":14784.0,"z":-6464.0}},{"classname":"light","origin":{"x":-14848.0,"y":14784.0,"z":-7168.0}},{"classname":"trigger_teleport","origin":{"x":-8417.99,"y":14784.0,"z":-10238.0}},{"model":116,"clusters":[1480,1787,1826],"classname":"func_brush","origin":{"x":-7934.0,"y":14784.0,"z":-10512.0}},{"model":117,"clusters":[2701,2702,2703,2704,2709,2710,2713,2714,2715,2716,2717,2718,2719,2720,2721,2722,2723,2724,2725,2726,2727,2728,2729,2730,2731,2732,2733,2734,2735,2736,2737,2738,2739,2740,2741,2742,2743,2787,2789,2790,2791,2792,2793,2794,2795,2796,2797,2798,2799,2800,2801,2802,2803,2827,2828,2855,2856,2857,2858,2859,2860,2861,2862,2863,2864,2865,2866,2867,2868,2869,2870,2876,2877,2878,2879,2880,2881,2882,2883,2884,2885,2886,2887,2888,2889,2890,2891,2894,2895,2897,2898,2899,2900,2901,2902,2903,2904,2905,2906,2907,2908,2909,2910,2911,2912,2913,2914,2915,2916,2917,2918,2919,2920,2921,2922,2923,2924,2925,2926,2927,2928,2929,2930,2931,2959,2960,2961,2962,2963,2964,2965,2969,2970,2971,2973,2974,2976,2977,2978,2979,2980,2985,2986,2987,2988,2989,2990,2991,2992,2993,2994,2995,2996,2997,2999,3000,3001,3002],"classname":"func_brush","origin":{"x":-10896.0,"y":4360.0,"z":-3096.0}},{"classname":"trigger_teleport","origin":{"x":-2784.0,"y":-1488.0,"z":1048.0}},{"targetname":"stage_selector","classname":"info_teleport_destination","origin":{"x":-6144.0,"y":-2048.0,"z":1184.0},"angles":{"x":0.0,"y":90.0,"z":0.0}},{"classname":"trigger_teleport","origin":{"x":-5724.0,"y":-1628.0,"z":1148.0}},{"classname":"trigger_teleport","origin":{"x":-6564.0,"y":-1628.0,"z":1148.0}},{"classname":"trigger_teleport","origin":{"x":-5724.0,"y":-2468.0,"z":1148.0}},{"classname":"trigger_teleport","origin":{"x":-6564.0,"y":-2468.0,"z":1148.0}},{"classname":"light","origin":{"x":-6384.0,"y":-1808.0,"z":1280.0}},{"classname":"light","origin":{"x":-5904.0,"y":-1808.0,"z":1280.0}},{"classname":"light","origin":{"x":-5904.0,"y":-2288.0,"z":1280.0}},{"classname":"light","origin":{"x":-6384.0,"y":-2288.0,"z":1280.0}},{"classname":"trigger_teleport","origin":{"x":-6144.0,"y":-2048.0,"z":1004.0}},{"classname":"trigger_teleport","origin":{"x":-3260.0,"y":-1856.0,"z":1328.0}},{"classname":"game_player_equip","origin":{"x":0.0,"y":0.0,"z":-1056.0}},{"classname":"trigger_multiple","origin":{"x":0.0,"y":0.0,"z":-608.0}},{"targetname":"stage2","classname":"trigger_multiple","origin":{"x":496.0,"y":-14336.0,"z":1488.0}},{"targetname":"stage3","classname":"trigger_multiple","origin":{"x":-10608.0,"y":4352.0,"z":1808.0}},{"targetname":"stage4_end","classname":"trigger_multiple","origin":{"x":-8417.5,"y":14784.0,"z":-10016.0}},{"targetname":"bonus","classname":"trigger_multiple","origin":{"x":12320.0,"y":15328.0,"z":-1200.0}},{"targetname":"bonus_end","classname":"trigger_multiple","origin":{"x":15360.0,"y":13824.0,"z":-2352.0}},{"classname":"env_spritetrail","origin":{"x":-6848.0,"y":4352.0,"z":-3496.0}},{"classname":"env_spritetrail","origin":{"x":-6836.0,"y":4352.0,"z":-3494.0}},{"classname":"env_spritetrail","origin":{"x":-6825.0,"y":4352.0,"z":-3487.0}},{"classname":"env_spritetrail","origin":{"x":-6818.0,"y":4352.0,"z":-3476.0}},{"classname":"env_spritetrail","origin":{"x":-6816.0,"y":4352.0,"z":-3464.0}},{"classname":"env_spritetrail","origin":{"x":-6818.0,"y":4352.0,"z":-3452.0}},{"classname":"env_spritetrail","origin":{"x":-6825.0,"y":4352.0,"z":-3441.0}},{"classname":"env_spritetrail","origin":{"x":-6836.0,"y":4352.0,"z":-3434.0}},{"classname":"env_spritetrail","origin":{"x":-6848.0,"y":4352.0,"z":-3432.0}},{"classname":"env_spritetrail","origin":{"x":-6860.0,"y":4352.0,"z":-3434.0}},{"classname":"env_spritetrail","origin":{"x":-6871.0,"y":4352.0,"z":-3441.0}},{"classname":"env_spritetrail","origin":{"x":-6878.0,"y":4352.0,"z":-3452.0}},{"classname":"env_spritetrail","origin":{"x":-6880.0,"y":4352.0,"z":-3464.0}},{"classname":"env_spritetrail","origin":{"x":-6878.0,"y":4352.0,"z":-3476.0}},{"classname":"env_spritetrail","origin":{"x":-6871.0,"y":4352.0,"z":-3487.0}},{"classname":"env_spritetrail","origin":{"x":-6860.0,"y":4352.0,"z":-3494.0}},{"targetname":"rot1","classname":"func_rotating","origin":{"x":-6848.0,"y":4352.0,"z":-3464.0},"angles":{"x":0.0,"y":0.0,"z":0.0}},{"targetname":"rot2","classname":"func_rotating","origin":{"x":-6848.0,"y":4352.0,"z":-3464.0},"angles":{"x":0.0,"y":0.0,"z":0.0}},{"targetname":"rot3","classname":"func_rotating","origin":{"x":-6848.0,"y":4352.0,"z":-3464.0},"angles":{"x":0.0,"y":0.0,"z":0.0}},{"classname":"env_spritetrail","origin":{"x":-6848.0,"y":4352.0,"z":-3496.0}},{"classname":"env_spritetrail","origin":{"x":-6848.0,"y":4364.0,"z":-3494.0}},{"classname":"env_spritetrail","origin":{"x":-6848.0,"y":4375.0,"z":-3487.0}},{"classname":"env_spritetrail","origin":{"x":-6848.0,"y":4382.0,"z":-3476.0}},{"classname":"env_spritetrail","origin":{"x":-6848.0,"y":4384.0,"z":-3464.0}},{"classname":"env_spritetrail","origin":{"x":-6848.0,"y":4382.0,"z":-3452.0}},{"classname":"env_spritetrail","origin":{"x":-6848.0,"y":4364.0,"z":-3434.0}},{"classname":"env_spritetrail","origin":{"x":-6848.0,"y":4375.0,"z":-3441.0}},{"classname":"env_spritetrail","origin":{"x":-6848.0,"y":4352.0,"z":-3432.0}},{"classname":"env_spritetrail","origin":{"x":-6848.0,"y":4340.0,"z":-3434.0}},{"classname":"env_spritetrail","origin":{"x":-6848.0,"y":4329.0,"z":-3441.0}},{"classname":"env_spritetrail","origin":{"x":-6848.0,"y":4322.0,"z":-3452.0}},{"classname":"env_spritetrail","origin":{"x":-6848.0,"y":4320.0,"z":-3464.0}},{"classname":"env_spritetrail","origin":{"x":-6848.0,"y":4322.0,"z":-3476.0}},{"classname":"env_spritetrail","origin":{"x":-6848.0,"y":4329.0,"z":-3487.0}},{"classname":"env_spritetrail","origin":{"x":-6848.0,"y":4340.0,"z":-3494.0}},{"classname":"env_spritetrail","origin":{"x":-6816.0,"y":4352.0,"z":-3464.0}},{"classname":"env_spritetrail","origin":{"x":-6818.0,"y":4364.0,"z":-3464.0}},{"classname":"env_spritetrail","origin":{"x":-6825.0,"y":4375.0,"z":-3464.0}},{"classname":"env_spritetrail","origin":{"x":-6836.0,"y":4382.0,"z":-3464.0}},{"classname":"env_spritetrail","origin":{"x":-6848.0,"y":4384.0,"z":-3464.0}},{"classname":"env_spritetrail","origin":{"x":-6860.0,"y":4382.0,"z":-3464.0}},{"classname":"env_spritetrail","origin":{"x":-6878.0,"y":4364.0,"z":-3464.0}},{"classname":"env_spritetrail","origin":{"x":-6871.0,"y":4375.0,"z":-3464.0}},{"classname":"env_spritetrail","origin":{"x":-6880.0,"y":4352.0,"z":-3464.0}},{"classname":"env_spritetrail","origin":{"x":-6878.0,"y":4340.0,"z":-3464.0}},{"classname":"env_spritetrail","origin":{"x":-6871.0,"y":4329.0,"z":-3464.0}},{"classname":"env_spritetrail","origin":{"x":-6860.0,"y":4322.0,"z":-3464.0}},{"classname":"env_spritetrail","origin":{"x":-6848.0,"y":4320.0,"z":-3464.0}},{"classname":"env_spritetrail","origin":{"x":-6836.0,"y":4322.0,"z":-3464.0}},{"classname":"env_spritetrail","origin":{"x":-6825.0,"y":4329.0,"z":-3464.0}},{"classname":"env_spritetrail","origin":{"x":-6818.0,"y":4340.0,"z":-3464.0}},{"classname":"func_rotating","origin":{"x":-6848.0,"y":4352.0,"z":-3464.0},"angles":{"x":0.0,"y":0.0,"z":0.0}},{"classname":"trigger_teleport","origin":{"x":-6848.0,"y":4352.0,"z":-3464.0}},{"classname":"water_lod_control"},{"model":0,"vertLighting":0,"flags":0,"clusters":[4154,4150,4148,4144,4126,4122,4120,4116],"classname":"prop_static","origin":{"x":12288.0,"y":-15104.0,"z":-3583.0},"angles":{"x":0.0,"y":0.0,"z":0.0}},{"model":0,"vertLighting":1,"flags":0,"clusters":[3998,3994,3992,3988,3969,3965,3962,3959],"classname":"prop_static","origin":{"x":12288.0,"y":-13568.0,"z":-3583.0},"angles":{"x":0.0,"y":180.0,"z":0.0}},{"model":2,"vertLighting":2,"flags":0,"clusters":[4368,4315],"classname":"prop_static","origin":{"x":3584.0,"y":-14400.0,"z":320.0},"angles":{"x":0.0,"y":0.0,"z":0.0}},{"model":2,"vertLighting":3,"flags":0,"clusters":[4296,4292],"classname":"prop_static","origin":{"x":5888.0,"y":-15040.0,"z":-256.0},"angles":{"x":0.0,"y":0.0,"z":0.0}},{"model":2,"vertLighting":4,"flags":0,"clusters":[4275,4271],"classname":"prop_static","origin":{"x":5888.0,"y":-13632.0,"z":-256.0},"angles":{"x":0.0,"y":180.0,"z":0.0}},{"model":0,"vertLighting":5,"flags":0,"clusters":[4681,4680,4678],"classname":"prop_static","origin":{"x":-2784.0,"y":-1856.0,"z":672.0},"angles":{"x":0.0,"y":0.0,"z":0.0}},{"model":2,"vertLighting":6,"flags":0,"clusters":[3041,3034],"classname":"prop_static","origin":{"x":-13216.0,"y":3680.0,"z":-3552.0},"angles":{"x":0.0,"y":0.0,"z":0.0}},{"model":2,"vertLighting":7,"flags":0,"clusters":[3053,2667],"classname":"prop_static","origin":{"x":-14880.0,"y":4992.0,"z":-3552.0},"angles":{"x":0.0,"y":0.0,"z":0.0}},{"model":1,"vertLighting":8,"flags":0,"clusters":[3026,3024],"classname":"prop_static","origin":{"x":-13632.0,"y":4640.0,"z":-3552.0},"angles":{"x":0.0,"y":0.0,"z":0.0}}]}