{"name":"surf_juturna_easy","lightmapUrl":"https://raw.githubusercontent.com/RSCSurf/SurfMaps4/main/maps/surf_juturna_easy/lightmap.json?v=2048-125ba","leafPages":[{"first":0,"count":4044,"url":"https://raw.githubusercontent.com/RSCSurf/SurfMaps4/main/maps/surf_juturna_easy/geom/leafpage0.json?v=2048-125ba"}],"dispPages":[{"first":0,"count":0,"url":"https://raw.githubusercontent.com/RSCSurf/SurfMaps4/main/maps/surf_juturna_easy/geom/disppage0.json?v=2048-125ba"}],"materialPages":[{"first":0,"count":26,"url":"https://raw.githubusercontent.com/RSCSurf/SurfMaps4/main/maps/surf_juturna_easy/materials/matpage0.json?v=2048-125ba"}],"brushModelPages":[{"first":0,"count":116,"url":"https://raw.githubusercontent.com/RSCSurf/SurfMaps4/main/maps/surf_juturna_easy/geom/bsppage0.json?v=2048-125ba"}],"studioModelPages":[{"first":0,"count":0,"url":"https://raw.githubusercontent.com/RSCSurf/SurfMaps4/main/maps/surf_juturna_easy/geom/mdlpage0.json?v=2048-125ba"}],"vertLightingPages":[{"first":0,"count":0,"url":"https://raw.githubusercontent.com/RSCSurf/SurfMaps4/main/maps/surf_juturna_easy/geom/vhvpage0.json?v=2048-125ba"}],"visPages":[{"first":0,"count":1284,"url":"https://raw.githubusercontent.com/RSCSurf/SurfMaps4/main/maps/surf_juturna_easy/geom/vispage0.json?v=2048-125ba"}],"ambientPages":[{"first":0,"count":4044,"url":"https://raw.githubusercontent.com/RSCSurf/SurfMaps4/main/maps/surf_juturna_easy/geom/ambientpage0.json?v=2048-125ba"}],"entities":[{"skyMaterial":{"shader":"SourceUtils.Shaders.Sky","properties":[{"name":"cullFace","type":1,"value":false},{"name":"facePosX","type":4,"value":"https://raw.githubusercontent.com/RSCSurf/SurfMaps4/main/maps/surf_juturna_easy/materials/skybox/lost_at_seart.vtf.json?v=2048-125ba"},{"name":"faceNegX","type":4,"value":"https://raw.githubusercontent.com/RSCSurf/SurfMaps4/main/maps/surf_juturna_easy/materials/skybox/lost_at_sealf.vtf.json?v=2048-125ba"},{"name":"facePosY","type":4,"value":"https://raw.githubusercontent.com/RSCSurf/SurfMaps4/main/maps/surf_juturna_easy/materials/skybox/lost_at_seabk.vtf.json?v=2048-125ba"},{"name":"faceNegY","type":4,"value":"https://raw.githubusercontent.com/RSCSurf/SurfMaps4/main/maps/surf_juturna_easy/materials/skybox/lost_at_seaft.vtf.json?v=2048-125ba"},{"name":"facePosZ","type":4,"value":"https://raw.githubusercontent.com/RSCSurf/SurfMaps4/main/maps/surf_juturna_easy/materials/skybox/lost_at_seaup.vtf.json?v=2048-125ba"},{"name":"faceNegZ","type":4,"value":"https://raw.githubusercontent.com/RSCSurf/SurfMaps4/main/maps/surf_juturna_easy/materials/skybox/lost_at_seadn.vtf.json?v=2048-125ba"}]},"model":0,"classname":"worldspawn"},{"classname":"infodecal","origin":{"x":5616.0,"y":-2.73523,"z":5384.93}},{"classname":"infodecal","origin":{"x":4368.0,"y":-323.163,"z":5386.33}},{"classname":"trigger_teleport","origin":{"x":-6312.0,"y":4.0,"z":-2757.45}},{"classname":"infodecal","origin":{"x":3405.98,"y":6.68731,"z":511.6}},{"classname":"trigger_teleport","origin":{"x":5628.0,"y":0.0,"z":5184.0}},{"classname":"trigger_teleport","origin":{"x":4000.0,"y":-908.0,"z":4896.0}},{"targetname":"spawn1","classname":"info_teleport_destination","origin":{"x":4928.0,"y":0.0,"z":5121.0},"angles":{"x":0.0,"y":180.0,"z":0.0}},{"classname":"trigger_teleport","origin":{"x":4000.0,"y":6784.0,"z":-2108.0}},{"classname":"trigger_teleport","origin":{"x":2880.0,"y":6784.0,"z":-1532.0}},{"classname":"trigger_teleport","origin":{"x":416.0,"y":6784.0,"z":-702.0}},{"classname":"light","origin":{"x":1520.0,"y":8032.0,"z":-224.0}},{"classname":"light","origin":{"x":1520.0,"y":5472.0,"z":-224.0}},{"classname":"light","origin":{"x":720.0,"y":7264.0,"z":-224.0}},{"classname":"light","origin":{"x":720.0,"y":6240.0,"z":-224.0}},{"classname":"trigger_teleport","origin":{"x":-5488.0,"y":6784.0,"z":1252.0}},{"classname":"light","origin":{"x":-1840.0,"y":8320.0,"z":832.0}},{"classname":"light","origin":{"x":-1840.0,"y":5248.0,"z":832.0}},{"classname":"trigger_teleport","origin":{"x":-7648.0,"y":6784.0,"z":1028.0}},{"classname":"trigger_teleport","origin":{"x":-7344.0,"y":5879.0,"z":484.0}},{"classname":"trigger_teleport","origin":{"x":-7344.0,"y":7689.0,"z":484.0}},{"classname":"trigger_teleport","origin":{"x":-7648.0,"y":6784.0,"z":484.0}},{"classname":"trigger_teleport","origin":{"x":-9664.0,"y":6784.0,"z":1426.0}},{"classname":"light","origin":{"x":-9296.0,"y":6400.0,"z":1696.0}},{"classname":"light","origin":{"x":-9296.0,"y":7168.0,"z":1696.0}},{"targetname":"s1","classname":"info_teleport_destination","origin":{"x":-10960.0,"y":6784.0,"z":2304.0},"angles":{"x":0.0,"y":0.0,"z":0.0}},{"classname":"trigger_teleport","origin":{"x":-2880.0,"y":6784.0,"z":-126.0}},{"classname":"trigger_teleport","origin":{"x":-11616.0,"y":6784.0,"z":2176.0}},{"classname":"light","origin":{"x":-10032.0,"y":6400.0,"z":1856.0}},{"classname":"light","origin":{"x":-10032.0,"y":7168.0,"z":1856.0}},{"classname":"light","origin":{"x":-7120.0,"y":6784.0,"z":1216.0}},{"classname":"light","origin":{"x":-7632.0,"y":6784.0,"z":1216.0}},{"classname":"light","origin":{"x":-8144.0,"y":6784.0,"z":1216.0}},{"classname":"light","origin":{"x":-8656.0,"y":6784.0,"z":1216.0}},{"classname":"light","origin":{"x":-6640.0,"y":6784.0,"z":1216.0}},{"classname":"trigger_teleport","origin":{"x":10656.0,"y":6879.98,"z":-328.0}},{"classname":"trigger_teleport","origin":{"x":6960.0,"y":6784.0,"z":-2352.0}},{"classname":"light","origin":{"x":-5840.0,"y":6400.0,"z":1600.0}},{"classname":"light","origin":{"x":-5840.0,"y":7168.0,"z":1600.0}},{"classname":"light","origin":{"x":-5072.0,"y":6400.0,"z":1600.0}},{"classname":"light","origin":{"x":-5072.0,"y":7168.0,"z":1600.0}},{"classname":"light","origin":{"x":-4208.0,"y":6400.0,"z":832.0}},{"classname":"light","origin":{"x":-4208.0,"y":7168.0,"z":832.0}},{"classname":"light","origin":{"x":-3440.0,"y":5600.0,"z":832.0}},{"classname":"light","origin":{"x":-3440.0,"y":7968.0,"z":832.0}},{"classname":"light","origin":{"x":-720.0,"y":5600.0,"z":832.0}},{"classname":"light","origin":{"x":-720.0,"y":7968.0,"z":832.0}},{"classname":"trigger_teleport","origin":{"x":9376.0,"y":6784.0,"z":-696.0}},{"classname":"light","origin":{"x":-528.0,"y":6240.0,"z":-416.0}},{"classname":"light","origin":{"x":-528.0,"y":7264.0,"z":-416.0}},{"classname":"light","origin":{"x":1040.0,"y":6400.0,"z":-1184.0}},{"classname":"light","origin":{"x":1040.0,"y":7168.0,"z":-1184.0}},{"classname":"light","origin":{"x":1968.0,"y":6400.0,"z":-1184.0}},{"classname":"light","origin":{"x":1968.0,"y":7168.0,"z":-1184.0}},{"classname":"light","origin":{"x":2864.0,"y":6400.0,"z":-1184.0}},{"classname":"light","origin":{"x":2864.0,"y":7168.0,"z":-1184.0}},{"classname":"light","origin":{"x":4720.0,"y":6784.0,"z":-1184.0}},{"classname":"light","origin":{"x":3952.0,"y":6784.0,"z":-1184.0}},{"classname":"light","origin":{"x":3808.0,"y":7680.0,"z":-1184.0}},{"classname":"light","origin":{"x":3808.0,"y":5920.0,"z":-1184.0}},{"classname":"light","origin":{"x":4096.0,"y":7680.0,"z":-1184.0}},{"classname":"light","origin":{"x":4096.0,"y":5920.0,"z":-1184.0}},{"classname":"light","origin":{"x":4384.0,"y":7680.0,"z":-1184.0}},{"classname":"light","origin":{"x":4384.0,"y":5920.0,"z":-1184.0}},{"targetname":"juxend1","classname":"trigger_multiple","origin":{"x":10016.0,"y":6784.0,"z":-232.0}},{"targetname":"juxstart1","classname":"trigger_multiple","origin":{"x":-10896.0,"y":6784.0,"z":2128.0}},{"classname":"light","origin":{"x":4960.0,"y":7680.0,"z":-1184.0}},{"classname":"light","origin":{"x":4960.0,"y":5920.0,"z":-1184.0}},{"classname":"light","origin":{"x":4672.0,"y":7680.0,"z":-1184.0}},{"classname":"light","origin":{"x":4672.0,"y":5920.0,"z":-1184.0}},{"classname":"info_player_terrorist","origin":{"x":5040.0,"y":240.0,"z":5152.0},"angles":{"x":0.0,"y":180.0,"z":0.0}},{"classname":"info_player_counterterrorist","origin":{"x":5040.0,"y":-240.0,"z":5152.0},"angles":{"x":0.0,"y":180.0,"z":0.0}},{"classname":"info_player_terrorist","origin":{"x":5088.0,"y":240.0,"z":5152.0},"angles":{"x":0.0,"y":180.0,"z":0.0}},{"classname":"info_player_counterterrorist","origin":{"x":5088.0,"y":-240.0,"z":5152.0},"angles":{"x":0.0,"y":180.0,"z":0.0}},{"classname":"info_player_terrorist","origin":{"x":5136.0,"y":240.0,"z":5152.0},"angles":{"x":0.0,"y":180.0,"z":0.0}},{"classname":"info_player_counterterrorist","origin":{"x":5136.0,"y":-240.0,"z":5152.0},"angles":{"x":0.0,"y":180.0,"z":0.0}},{"classname":"info_player_terrorist","origin":{"x":5280.0,"y":240.0,"z":5152.0},"angles":{"x":0.0,"y":180.0,"z":0.0}},{"classname":"info_player_counterterrorist","origin":{"x":5280.0,"y":-240.0,"z":5152.0},"angles":{"x":0.0,"y":180.0,"z":0.0}},{"classname":"info_player_terrorist","origin":{"x":5328.0,"y":240.0,"z":5152.0},"angles":{"x":0.0,"y":180.0,"z":0.0}},{"classname":"info_player_counterterrorist","origin":{"x":5328.0,"y":-240.0,"z":5152.0},"angles":{"x":0.0,"y":180.0,"z":0.0}},{"classname":"info_player_terrorist","origin":{"x":5232.0,"y":240.0,"z":5152.0},"angles":{"x":0.0,"y":180.0,"z":0.0}},{"classname":"info_player_counterterrorist","origin":{"x":5232.0,"y":-240.0,"z":5152.0},"angles":{"x":0.0,"y":180.0,"z":0.0}},{"classname":"info_player_terrorist","origin":{"x":5184.0,"y":240.0,"z":5152.0},"angles":{"x":0.0,"y":180.0,"z":0.0}},{"classname":"info_player_counterterrorist","origin":{"x":5184.0,"y":-240.0,"z":5152.0},"angles":{"x":0.0,"y":180.0,"z":0.0}},{"classname":"info_player_terrorist","origin":{"x":5088.0,"y":192.0,"z":5152.0},"angles":{"x":0.0,"y":180.0,"z":0.0}},{"classname":"info_player_counterterrorist","origin":{"x":5088.0,"y":-288.0,"z":5152.0},"angles":{"x":0.0,"y":180.0,"z":0.0}},{"classname":"info_player_terrorist","origin":{"x":5136.0,"y":192.0,"z":5152.0},"angles":{"x":0.0,"y":180.0,"z":0.0}},{"classname":"info_player_counterterrorist","origin":{"x":5136.0,"y":-288.0,"z":5152.0},"angles":{"x":0.0,"y":180.0,"z":0.0}},{"classname":"info_player_terrorist","origin":{"x":5040.0,"y":192.0,"z":5152.0},"angles":{"x":0.0,"y":180.0,"z":0.0}},{"classname":"info_player_counterterrorist","origin":{"x":5040.0,"y":-288.0,"z":5152.0},"angles":{"x":0.0,"y":180.0,"z":0.0}},{"classname":"info_player_terrorist","origin":{"x":4992.0,"y":192.0,"z":5152.0},"angles":{"x":0.0,"y":180.0,"z":0.0}},{"classname":"info_player_counterterrorist","origin":{"x":4992.0,"y":-288.0,"z":5152.0},"angles":{"x":0.0,"y":180.0,"z":0.0}},{"classname":"info_player_terrorist","origin":{"x":5280.0,"y":192.0,"z":5152.0},"angles":{"x":0.0,"y":180.0,"z":0.0}},{"classname":"info_player_counterterrorist","origin":{"x":5280.0,"y":-288.0,"z":5152.0},"angles":{"x":0.0,"y":180.0,"z":0.0}},{"classname":"info_player_terrorist","origin":{"x":5328.0,"y":192.0,"z":5152.0},"angles":{"x":0.0,"y":180.0,"z":0.0}},{"classname":"info_player_counterterrorist","origin":{"x":5328.0,"y":-288.0,"z":5152.0},"angles":{"x":0.0,"y":180.0,"z":0.0}},{"classname":"info_player_terrorist","origin":{"x":5232.0,"y":192.0,"z":5152.0},"angles":{"x":0.0,"y":180.0,"z":0.0}},{"classname":"info_player_counterterrorist","origin":{"x":5232.0,"y":-288.0,"z":5152.0},"angles":{"x":0.0,"y":180.0,"z":0.0}},{"classname":"info_player_terrorist","origin":{"x":5184.0,"y":192.0,"z":5152.0},"angles":{"x":0.0,"y":180.0,"z":0.0}},{"classname":"info_player_counterterrorist","origin":{"x":5184.0,"y":-288.0,"z":5152.0},"angles":{"x":0.0,"y":180.0,"z":0.0}},{"classname":"info_player_terrorist","origin":{"x":5280.0,"y":288.0,"z":5152.0},"angles":{"x":0.0,"y":180.0,"z":0.0}},{"classname":"info_player_counterterrorist","origin":{"x":5280.0,"y":-192.0,"z":5152.0},"angles":{"x":0.0,"y":180.0,"z":0.0}},{"classname":"info_player_terrorist","origin":{"x":5328.0,"y":288.0,"z":5152.0},"angles":{"x":0.0,"y":180.0,"z":0.0}},{"classname":"info_player_counterterrorist","origin":{"x":5328.0,"y":-192.0,"z":5152.0},"angles":{"x":0.0,"y":180.0,"z":0.0}},{"classname":"info_player_terrorist","origin":{"x":5232.0,"y":288.0,"z":5152.0},"angles":{"x":0.0,"y":180.0,"z":0.0}},{"classname":"info_player_counterterrorist","origin":{"x":5232.0,"y":-192.0,"z":5152.0},"angles":{"x":0.0,"y":180.0,"z":0.0}},{"classname":"info_player_terrorist","origin":{"x":5184.0,"y":288.0,"z":5152.0},"angles":{"x":0.0,"y":180.0,"z":0.0}},{"classname":"info_player_counterterrorist","origin":{"x":5184.0,"y":-192.0,"z":5152.0},"angles":{"x":0.0,"y":180.0,"z":0.0}},{"classname":"info_player_terrorist","origin":{"x":5088.0,"y":288.0,"z":5152.0},"angles":{"x":0.0,"y":180.0,"z":0.0}},{"classname":"info_player_counterterrorist","origin":{"x":5088.0,"y":-192.0,"z":5152.0},"angles":{"x":0.0,"y":180.0,"z":0.0}},{"classname":"info_player_terrorist","origin":{"x":5136.0,"y":288.0,"z":5152.0},"angles":{"x":0.0,"y":180.0,"z":0.0}},{"classname":"info_player_counterterrorist","origin":{"x":5136.0,"y":-192.0,"z":5152.0},"angles":{"x":0.0,"y":180.0,"z":0.0}},{"classname":"info_player_terrorist","origin":{"x":5040.0,"y":288.0,"z":5152.0},"angles":{"x":0.0,"y":180.0,"z":0.0}},{"classname":"info_player_counterterrorist","origin":{"x":5040.0,"y":-192.0,"z":5152.0},"angles":{"x":0.0,"y":180.0,"z":0.0}},{"classname":"info_player_terrorist","origin":{"x":4992.0,"y":288.0,"z":5152.0},"angles":{"x":0.0,"y":180.0,"z":0.0}},{"classname":"info_player_counterterrorist","origin":{"x":4992.0,"y":-192.0,"z":5152.0},"angles":{"x":0.0,"y":180.0,"z":0.0}},{"classname":"info_player_terrorist","origin":{"x":4896.0,"y":288.0,"z":5152.0},"angles":{"x":0.0,"y":180.0,"z":0.0}},{"classname":"info_player_counterterrorist","origin":{"x":4896.0,"y":-192.0,"z":5152.0},"angles":{"x":0.0,"y":180.0,"z":0.0}},{"classname":"info_player_terrorist","origin":{"x":4944.0,"y":288.0,"z":5152.0},"angles":{"x":0.0,"y":180.0,"z":0.0}},{"classname":"info_player_counterterrorist","origin":{"x":4944.0,"y":-192.0,"z":5152.0},"angles":{"x":0.0,"y":180.0,"z":0.0}},{"classname":"info_player_terrorist","origin":{"x":4848.0,"y":288.0,"z":5152.0},"angles":{"x":0.0,"y":180.0,"z":0.0}},{"classname":"info_player_counterterrorist","origin":{"x":4848.0,"y":-192.0,"z":5152.0},"angles":{"x":0.0,"y":180.0,"z":0.0}},{"classname":"info_player_terrorist","origin":{"x":4800.0,"y":288.0,"z":5152.0},"angles":{"x":0.0,"y":180.0,"z":0.0}},{"classname":"info_player_counterterrorist","origin":{"x":4800.0,"y":-192.0,"z":5152.0},"angles":{"x":0.0,"y":180.0,"z":0.0}},{"classname":"info_player_terrorist","origin":{"x":4896.0,"y":240.0,"z":5152.0},"angles":{"x":0.0,"y":180.0,"z":0.0}},{"classname":"info_player_counterterrorist","origin":{"x":4896.0,"y":-240.0,"z":5152.0},"angles":{"x":0.0,"y":180.0,"z":0.0}},{"classname":"info_player_terrorist","origin":{"x":4944.0,"y":240.0,"z":5152.0},"angles":{"x":0.0,"y":180.0,"z":0.0}},{"classname":"info_player_counterterrorist","origin":{"x":4944.0,"y":-240.0,"z":5152.0},"angles":{"x":0.0,"y":180.0,"z":0.0}},{"classname":"info_player_terrorist","origin":{"x":4848.0,"y":240.0,"z":5152.0},"angles":{"x":0.0,"y":180.0,"z":0.0}},{"classname":"info_player_counterterrorist","origin":{"x":4848.0,"y":-240.0,"z":5152.0},"angles":{"x":0.0,"y":180.0,"z":0.0}},{"classname":"info_player_terrorist","origin":{"x":4800.0,"y":240.0,"z":5152.0},"angles":{"x":0.0,"y":180.0,"z":0.0}},{"classname":"info_player_counterterrorist","origin":{"x":4800.0,"y":-240.0,"z":5152.0},"angles":{"x":0.0,"y":180.0,"z":0.0}},{"classname":"info_player_terrorist","origin":{"x":4896.0,"y":192.0,"z":5152.0},"angles":{"x":0.0,"y":180.0,"z":0.0}},{"classname":"info_player_counterterrorist","origin":{"x":4896.0,"y":-288.0,"z":5152.0},"angles":{"x":0.0,"y":180.0,"z":0.0}},{"classname":"info_player_terrorist","origin":{"x":4944.0,"y":192.0,"z":5152.0},"angles":{"x":0.0,"y":180.0,"z":0.0}},{"classname":"info_player_counterterrorist","origin":{"x":4944.0,"y":-288.0,"z":5152.0},"angles":{"x":0.0,"y":180.0,"z":0.0}},{"classname":"info_player_terrorist","origin":{"x":4848.0,"y":192.0,"z":5152.0},"angles":{"x":0.0,"y":180.0,"z":0.0}},{"classname":"info_player_counterterrorist","origin":{"x":4848.0,"y":-288.0,"z":5152.0},"angles":{"x":0.0,"y":180.0,"z":0.0}},{"classname":"info_player_terrorist","origin":{"x":4800.0,"y":192.0,"z":5152.0},"angles":{"x":0.0,"y":180.0,"z":0.0}},{"classname":"info_player_counterterrorist","origin":{"x":4800.0,"y":-288.0,"z":5152.0},"angles":{"x":0.0,"y":180.0,"z":0.0}},{"classname":"info_player_terrorist","origin":{"x":4704.0,"y":288.0,"z":5152.0},"angles":{"x":0.0,"y":180.0,"z":0.0}},{"classname":"info_player_counterterrorist","origin":{"x":4704.0,"y":-192.0,"z":5152.0},"angles":{"x":0.0,"y":180.0,"z":0.0}},{"classname":"info_player_terrorist","origin":{"x":4752.0,"y":288.0,"z":5152.0},"angles":{"x":0.0,"y":180.0,"z":0.0}},{"classname":"info_player_counterterrorist","origin":{"x":4752.0,"y":-192.0,"z":5152.0},"angles":{"x":0.0,"y":180.0,"z":0.0}},{"classname":"info_player_terrorist","origin":{"x":4656.0,"y":288.0,"z":5152.0},"angles":{"x":0.0,"y":180.0,"z":0.0}},{"classname":"info_player_counterterrorist","origin":{"x":4656.0,"y":-192.0,"z":5152.0},"angles":{"x":0.0,"y":180.0,"z":0.0}},{"classname":"info_player_terrorist","origin":{"x":4608.0,"y":288.0,"z":5152.0},"angles":{"x":0.0,"y":180.0,"z":0.0}},{"classname":"info_player_counterterrorist","origin":{"x":4608.0,"y":-192.0,"z":5152.0},"angles":{"x":0.0,"y":180.0,"z":0.0}},{"classname":"info_player_terrorist","origin":{"x":4704.0,"y":240.0,"z":5152.0},"angles":{"x":0.0,"y":180.0,"z":0.0}},{"classname":"info_player_counterterrorist","origin":{"x":4704.0,"y":-240.0,"z":5152.0},"angles":{"x":0.0,"y":180.0,"z":0.0}},{"classname":"info_player_terrorist","origin":{"x":4752.0,"y":240.0,"z":5152.0},"angles":{"x":0.0,"y":180.0,"z":0.0}},{"classname":"info_player_counterterrorist","origin":{"x":4752.0,"y":-240.0,"z":5152.0},"angles":{"x":0.0,"y":180.0,"z":0.0}},{"classname":"info_player_terrorist","origin":{"x":4656.0,"y":240.0,"z":5152.0},"angles":{"x":0.0,"y":180.0,"z":0.0}},{"classname":"info_player_counterterrorist","origin":{"x":4656.0,"y":-240.0,"z":5152.0},"angles":{"x":0.0,"y":180.0,"z":0.0}},{"classname":"info_player_terrorist","origin":{"x":4608.0,"y":240.0,"z":5152.0},"angles":{"x":0.0,"y":180.0,"z":0.0}},{"classname":"info_player_counterterrorist","origin":{"x":4608.0,"y":-240.0,"z":5152.0},"angles":{"x":0.0,"y":180.0,"z":0.0}},{"classname":"info_player_terrorist","origin":{"x":4704.0,"y":192.0,"z":5152.0},"angles":{"x":0.0,"y":180.0,"z":0.0}},{"classname":"info_player_counterterrorist","origin":{"x":4704.0,"y":-288.0,"z":5152.0},"angles":{"x":0.0,"y":180.0,"z":0.0}},{"classname":"info_player_terrorist","origin":{"x":4752.0,"y":192.0,"z":5152.0},"angles":{"x":0.0,"y":180.0,"z":0.0}},{"classname":"info_player_counterterrorist","origin":{"x":4752.0,"y":-288.0,"z":5152.0},"angles":{"x":0.0,"y":180.0,"z":0.0}},{"classname":"info_player_terrorist","origin":{"x":4656.0,"y":192.0,"z":5152.0},"angles":{"x":0.0,"y":180.0,"z":0.0}},{"classname":"info_player_counterterrorist","origin":{"x":4656.0,"y":-288.0,"z":5152.0},"angles":{"x":0.0,"y":180.0,"z":0.0}},{"classname":"info_player_terrorist","origin":{"x":4608.0,"y":192.0,"z":5152.0},"angles":{"x":0.0,"y":180.0,"z":0.0}},{"classname":"info_player_counterterrorist","origin":{"x":4608.0,"y":-288.0,"z":5152.0},"angles":{"x":0.0,"y":180.0,"z":0.0}},{"classname":"trigger_teleport","origin":{"x":232.0,"y":0.0,"z":-13368.0}},{"classname":"light","origin":{"x":-1376.0,"y":0.0,"z":-13056.0}},{"classname":"light","origin":{"x":-2016.0,"y":0.0,"z":-13056.0}},{"classname":"light","origin":{"x":-1792.0,"y":0.0,"z":-14336.0}},{"classname":"trigger_teleport","origin":{"x":4356.0,"y":0.0,"z":5184.0}},{"classname":"light","origin":{"x":2238.79,"y":-1024.0,"z":3040.0}},{"classname":"light","origin":{"x":2240.0,"y":879.028,"z":3040.0}},{"model":22,"clusters":[271,278,284,286,288,299,303,305,320,321,322,323,324,354,355,364,365,418,423,426,448,459,472,473,475,476,484,485,498,499,557,562,565,585,596,780,817,838,982,1001,1022],"classname":"func_brush","origin":{"x":4419.5,"y":0.3,"z":1800.81}},{"classname":"light","origin":{"x":-2048.0,"y":0.0,"z":-5280.0}},{"Brightness":{"R":252,"G":251,"B":216,"A":200},"Ambient":{"R":255,"G":255,"B":255,"A":20},"BrightnessHdr":{"R":255,"G":255,"B":255,"A":1},"AmbientHdr":{"R":255,"G":255,"B":255,"A":1},"BrightnessScaleHdr":1.0,"AmbientScaleHdr":1.0,"Pitch":-72.0,"classname":"light_environment","origin":{"x":3009.85,"y":-349.283,"z":5023.77},"angles":{"x":-72.0,"y":118.0,"z":0.0}},{"model":23,"clusters":[450,451,587,588],"classname":"func_brush","origin":{"x":1744.0,"y":0.0,"z":-9488.0}},{"model":24,"clusters":[450,451,587,588],"classname":"func_brush","origin":{"x":1744.0,"y":0.0,"z":-9232.0}},{"model":25,"clusters":[1104,1133,1158,1163,1250,1261,1264],"classname":"func_brush","origin":{"x":-6272.0,"y":-1008.0,"z":-10768.0}},{"model":26,"clusters":[1264],"classname":"func_brush","origin":{"x":-9200.0,"y":-352.0,"z":-10880.0}},{"model":27,"clusters":[1217],"classname":"func_brush","origin":{"x":-9200.0,"y":352.0,"z":-10880.0}},{"model":28,"clusters":[587],"classname":"func_brush","origin":{"x":1744.0,"y":-336.0,"z":-9360.0}},{"model":29,"clusters":[587],"classname":"func_brush","origin":{"x":1744.0,"y":-192.0,"z":-9360.0}},{"model":30,"clusters":[451],"classname":"func_brush","origin":{"x":1744.0,"y":192.0,"z":-9360.0}},{"model":31,"clusters":[451],"classname":"func_brush","origin":{"x":1744.0,"y":336.0,"z":-9360.0}},{"model":32,"clusters":[1038],"classname":"func_brush","origin":{"x":-2416.0,"y":-352.0,"z":-3776.0}},{"model":33,"clusters":[1038],"classname":"func_brush","origin":{"x":-2416.0,"y":-496.0,"z":-3776.0}},{"model":34,"clusters":[852],"classname":"func_brush","origin":{"x":-2416.0,"y":352.0,"z":-3776.0}},{"model":35,"clusters":[852],"classname":"func_brush","origin":{"x":-2416.0,"y":496.0,"z":-3776.0}},{"model":36,"clusters":[1080],"classname":"func_brush","origin":{"x":-3205.87,"y":-336.0,"z":-528.0}},{"model":37,"clusters":[1080],"classname":"func_brush","origin":{"x":-3205.87,"y":-192.0,"z":-528.0}},{"model":38,"clusters":[875],"classname":"func_brush","origin":{"x":-3205.87,"y":192.0,"z":-528.0}},{"model":39,"clusters":[875],"classname":"func_brush","origin":{"x":-3205.87,"y":336.0,"z":-528.0}},{"model":40,"clusters":[271],"classname":"func_brush","origin":{"x":11222.8,"y":336.0,"z":2928.0}},{"model":41,"clusters":[271],"classname":"func_brush","origin":{"x":11222.8,"y":192.0,"z":2928.0}},{"model":42,"clusters":[288],"classname":"func_brush","origin":{"x":11222.8,"y":-192.0,"z":2928.0}},{"model":43,"clusters":[288],"classname":"func_brush","origin":{"x":11222.8,"y":-336.0,"z":2928.0}},{"model":44,"clusters":[558],"classname":"func_brush","origin":{"x":3421.98,"y":-380.68,"z":1392.0}},{"model":45,"clusters":[558],"classname":"func_brush","origin":{"x":3421.98,"y":-215.82,"z":1392.0}},{"model":46,"clusters":[419],"classname":"func_brush","origin":{"x":3421.98,"y":223.82,"z":1392.0}},{"model":47,"clusters":[419],"classname":"func_brush","origin":{"x":3421.98,"y":388.68,"z":1392.0}},{"classname":"trigger_teleport","origin":{"x":-5456.0,"y":-335.99,"z":-6894.0}},{"classname":"trigger_teleport","origin":{"x":-5456.0,"y":336.01,"z":-6894.0}},{"classname":"trigger_teleport","origin":{"x":-5456.0,"y":0.0,"z":-7152.0}},{"classname":"light","origin":{"x":3968.0,"y":0.0,"z":4976.0}},{"model":51,"clusters":[325,356,367,419,427,428,429,430,449,460,477,486,501,558,566,567,568,586,597,781,818,839,844,983,1002,1023,1028],"classname":"func_brush","origin":{"x":1899.26,"y":0.1,"z":-961.56}},{"model":52,"clusters":[868,869,875,1080,1110,1180],"classname":"func_brush","origin":{"x":-3205.71,"y":-0.12,"z":-656.26}},{"model":53,"clusters":[868,869,875,1080,1110,1180],"classname":"func_brush","origin":{"x":-3205.61,"y":0.19,"z":-400.0}},{"model":54,"clusters":[854,878,892,924,947,969,1037,1083,1097,1119,1140,1161,1205,1248],"classname":"func_brush","origin":{"x":-4392.0,"y":0.78,"z":-5015.43}},{"model":55,"clusters":[813,852],"classname":"func_brush","origin":{"x":-2416.0,"y":889.5,"z":-3600.0}},{"model":56,"clusters":[813,852,854],"classname":"func_brush","origin":{"x":-2416.0,"y":886.5,"z":-3952.0}},{"model":57,"clusters":[1038,1070],"classname":"func_brush","origin":{"x":-2416.0,"y":-886.6,"z":-3600.0}},{"model":58,"clusters":[1038,1070],"classname":"func_brush","origin":{"x":-2416.0,"y":-886.5,"z":-3952.0}},{"model":59,"clusters":[948,1141],"classname":"func_brush","origin":{"x":-5872.0,"y":0.0,"z":-5392.0}},{"model":60,"clusters":[948,1141],"classname":"func_brush","origin":{"x":-5872.0,"y":8.0,"z":-5648.0}},{"model":61,"clusters":[893,925,948],"classname":"func_brush","origin":{"x":-4592.0,"y":720.0,"z":-5648.0}},{"model":62,"clusters":[893,925,948],"classname":"func_brush","origin":{"x":-4592.0,"y":720.0,"z":-5392.0}},{"model":63,"clusters":[1098,1120,1141],"classname":"func_brush","origin":{"x":-4592.0,"y":-720.0,"z":-5392.0}},{"model":64,"clusters":[1098,1120,1141],"classname":"func_brush","origin":{"x":-4592.0,"y":-720.0,"z":-5648.0}},{"model":65,"clusters":[598,986,1009,1013,1040],"classname":"func_brush","origin":{"x":-1024.0,"y":-528.0,"z":-7696.0}},{"model":66,"clusters":[598,986,1009,1013,1040],"classname":"func_brush","origin":{"x":-1024.0,"y":-528.0,"z":-7952.0}},{"model":67,"clusters":[462,786,787,824,827,828,831,861,880],"classname":"func_brush","origin":{"x":-1024.0,"y":528.0,"z":-7952.0}},{"model":68,"clusters":[462,786,787,824,827,828,831,861,880],"classname":"func_brush","origin":{"x":-1024.0,"y":528.0,"z":-7696.0}},{"model":69,"clusters":[462,598],"classname":"func_brush","origin":{"x":1008.0,"y":0.0,"z":-7696.0}},{"model":70,"clusters":[462,598],"classname":"func_brush","origin":{"x":1008.0,"y":0.0,"z":-7952.0}},{"model":71,"clusters":[894,897,933,1099,1102,1124],"classname":"func_brush","origin":{"x":-4208.0,"y":-0.31,"z":-7119.58}},{"model":72,"clusters":[451,462,587,598,787,827,831,861,985,1008,1012,1040],"classname":"func_brush","origin":{"x":-656.02,"y":0.0,"z":-9936.0}},{"model":73,"clusters":[450,461,783,822,856,882],"classname":"func_brush","origin":{"x":-768.0,"y":976.0,"z":-9232.0}},{"model":74,"clusters":[450,461,783,822,856,882],"classname":"func_brush","origin":{"x":-768.0,"y":976.0,"z":-9488.0}},{"model":75,"clusters":[588,599,990,1015,1044,1089],"classname":"func_brush","origin":{"x":-768.0,"y":-976.0,"z":-9488.0}},{"model":76,"clusters":[588,599,990,1015,1044,1089],"classname":"func_brush","origin":{"x":-768.0,"y":-976.0,"z":-9232.0}},{"model":77,"clusters":[1104,1133,1158,1163,1250,1261,1264],"classname":"func_brush","origin":{"x":-6272.0,"y":-1008.0,"z":-11024.0}},{"model":78,"clusters":[899,929,954,971,1207,1214,1217],"classname":"func_brush","origin":{"x":-6272.0,"y":1008.0,"z":-11024.0}},{"model":79,"clusters":[899,929,954,971,1207,1214,1217],"classname":"func_brush","origin":{"x":-6272.0,"y":1008.0,"z":-10768.0}},{"model":80,"clusters":[899,937,966,971,1104,1128,1154,1163,1207,1214,1217,1250,1261,1264],"classname":"func_brush","origin":{"x":-6272.02,"y":0.0,"z":-13232.0}},{"model":81,"clusters":[837,867,888,889,904,938,967,972,1021,1051,1086,1088,1109,1134,1155,1164,1208,1215,1218,1222,1225,1226,1251,1262,1265,1271,1275,1276],"classname":"func_brush","origin":{"x":-5520.03,"y":0.0,"z":-16080.0}},{"classname":"light","origin":{"x":-4480.0,"y":11.5187,"z":-7808.0}},{"classname":"trigger_teleport","origin":{"x":-1008.0,"y":0.0,"z":-13576.0}},{"classname":"light","origin":{"x":-2736.0,"y":0.0,"z":-13824.0}},{"classname":"light","origin":{"x":-1520.0,"y":0.0,"z":-14992.0}},{"classname":"trigger_teleport","origin":{"x":-2800.0,"y":0.0,"z":-14572.0}},{"targetname":"tele1","classname":"info_teleport_destination","origin":{"x":3860.56,"y":-0.459473,"z":4950.48},"angles":{"x":0.0,"y":180.0,"z":0.0}},{"classname":"trigger_teleport","origin":{"x":-5520.0,"y":0.0,"z":-16108.0}},{"classname":"trigger_teleport","origin":{"x":-6272.0,"y":0.0,"z":-13256.0}},{"classname":"trigger_teleport","origin":{"x":-784.0,"y":-784.0,"z":-11752.0}},{"classname":"trigger_teleport","origin":{"x":-784.0,"y":784.0,"z":-11752.0}},{"classname":"trigger_teleport","origin":{"x":-655.9,"y":0.0,"z":-9967.07}},{"classname":"trigger_teleport","origin":{"x":-4480.0,"y":0.0,"z":-8808.0}},{"classname":"trigger_teleport","origin":{"x":-4208.0,"y":0.0,"z":-7144.0}},{"classname":"trigger_teleport","origin":{"x":-5488.0,"y":-656.0,"z":-7144.0}},{"classname":"trigger_teleport","origin":{"x":-5856.0,"y":0.0,"z":-7144.0}},{"classname":"trigger_teleport","origin":{"x":-5488.0,"y":656.0,"z":-7144.0}},{"classname":"trigger_teleport","origin":{"x":-1856.0,"y":0.0,"z":-6376.0}},{"classname":"trigger_teleport","origin":{"x":-632.0,"y":0.0,"z":-4716.0}},{"classname":"trigger_teleport","origin":{"x":-1048.0,"y":0.0,"z":-4328.0}},{"classname":"trigger_teleport","origin":{"x":-1824.0,"y":0.0,"z":-3983.93}},{"classname":"trigger_teleport","origin":{"x":-4384.0,"y":0.0,"z":-5042.88}},{"classname":"trigger_teleport","origin":{"x":-4000.0,"y":0.0,"z":-3314.88}},{"classname":"trigger_teleport","origin":{"x":-2004.14,"y":1131.88,"z":-2514.88}},{"classname":"trigger_teleport","origin":{"x":-2004.14,"y":1926.6,"z":-2321.88}},{"classname":"trigger_teleport","origin":{"x":-2807.24,"y":1914.56,"z":-1545.88}},{"classname":"trigger_teleport","origin":{"x":-2810.74,"y":0.0,"z":-1545.88}},{"classname":"trigger_teleport","origin":{"x":-2807.24,"y":-1914.56,"z":-1545.88}},{"classname":"trigger_teleport","origin":{"x":-2004.14,"y":-1926.6,"z":-2321.88}},{"classname":"trigger_teleport","origin":{"x":-2004.14,"y":-1131.88,"z":-2514.88}},{"classname":"trigger_teleport","origin":{"x":1912.3,"y":0.0,"z":-988.88}},{"classname":"trigger_teleport","origin":{"x":5828.86,"y":-1914.56,"z":-988.88}},{"classname":"trigger_teleport","origin":{"x":5828.86,"y":1914.56,"z":-988.88}},{"classname":"trigger_teleport","origin":{"x":8728.05,"y":-1926.6,"z":126.12}},{"classname":"trigger_teleport","origin":{"x":8728.04,"y":1926.6,"z":126.12}},{"classname":"trigger_teleport","origin":{"x":4422.85,"y":0.0,"z":1773.88}},{"classname":"trigger_teleport","origin":{"x":4322.8,"y":1770.06,"z":1264.88}},{"classname":"trigger_teleport","origin":{"x":4321.8,"y":-1770.06,"z":1264.88}},{"classname":"trigger_teleport","origin":{"x":1490.2,"y":0.0,"z":3420.88}},{"classname":"light","origin":{"x":-10752.0,"y":0.0,"z":-12160.0}},{"classname":"light","origin":{"x":-8192.0,"y":0.0,"z":-13952.0}},{"classname":"light","origin":{"x":-4608.66,"y":0.0,"z":-13952.0}},{"classname":"light","origin":{"x":-2816.0,"y":0.0,"z":-12224.0}},{"classname":"light","origin":{"x":-2816.0,"y":0.0,"z":-3520.0}},{"classname":"light","origin":{"x":-896.0,"y":0.0,"z":-3632.0}},{"classname":"light","origin":{"x":-5504.0,"y":0.0,"z":-5828.0}},{"classname":"light","origin":{"x":-2560.0,"y":0.0,"z":-7696.0}},{"classname":"light","origin":{"x":384.0,"y":0.0,"z":-7808.0}},{"classname":"light","origin":{"x":-672.0,"y":0.0,"z":-4832.0}},{"classname":"light","origin":{"x":1408.0,"y":0.0,"z":-9088.0}},{"classname":"light","origin":{"x":-1024.0,"y":-768.0,"z":-9728.0}},{"classname":"light","origin":{"x":-1024.0,"y":768.0,"z":-9744.0}},{"classname":"light","origin":{"x":3104.0,"y":-963.299,"z":1152.0}},{"classname":"light","origin":{"x":3104.0,"y":963.299,"z":1152.0}},{"classname":"light","origin":{"x":0.0,"y":0.0,"z":1152.0}},{"classname":"light","origin":{"x":-1536.0,"y":0.0,"z":1152.0}},{"classname":"light","origin":{"x":-2816.0,"y":0.0,"z":-384.0}},{"classname":"light","origin":{"x":-2016.0,"y":1926.6,"z":-1056.0}},{"classname":"light","origin":{"x":-2016.0,"y":-1926.6,"z":-1056.0}},{"classname":"light","origin":{"x":-4608.0,"y":0.0,"z":-1696.0}},{"classname":"info_player_terrorist","origin":{"x":4992.0,"y":240.0,"z":5152.0},"angles":{"x":0.0,"y":180.0,"z":0.0}},{"classname":"info_player_counterterrorist","origin":{"x":4992.0,"y":-240.0,"z":5152.0},"angles":{"x":0.0,"y":180.0,"z":0.0}},{"classname":"light","origin":{"x":576.0,"y":1.04791,"z":4832.0}},{"classname":"light","origin":{"x":16.0,"y":-1.17773,"z":4736.0}},{"classname":"light","origin":{"x":-2048.0,"y":0.0,"z":4736.0}},{"classname":"light","origin":{"x":-1872.0,"y":0.0,"z":2352.0}},{"classname":"light","origin":{"x":384.0,"y":0.0,"z":3200.0}},{"classname":"light","origin":{"x":5120.0,"y":0.0,"z":3200.0}},{"classname":"light","origin":{"x":8192.0,"y":-1920.0,"z":1792.0}},{"classname":"light","origin":{"x":8192.0,"y":1920.0,"z":1808.0}},{"classname":"light","origin":{"x":4480.0,"y":0.0,"z":1408.0}},{"classname":"light","origin":{"x":1536.0,"y":0.0,"z":1152.0}}]}